<chromosome id="15006" primary-parent-id="10819" secondary-parent-id="10765"><neuron id="0" type="in" activation="linear"/>
<neuron id="1" type="in" activation="linear"/>
<neuron id="2" type="in" activation="linear"/>
<neuron id="3" type="in" activation="linear"/>
<neuron id="4" type="in" activation="linear"/>
<neuron id="5" type="in" activation="linear"/>
<neuron id="6" type="in" activation="linear"/>
<neuron id="7" type="in" activation="linear"/>
<neuron id="8" type="in" activation="linear"/>
<neuron id="9" type="in" activation="linear"/>
<neuron id="10" type="in" activation="linear"/>
<neuron id="11" type="in" activation="linear"/>
<neuron id="12" type="in" activation="linear"/>
<neuron id="13" type="in" activation="linear"/>
<neuron id="14" type="in" activation="linear"/>
<neuron id="15" type="in" activation="linear"/>
<neuron id="16" type="in" activation="linear"/>
<neuron id="17" type="in" activation="linear"/>
<neuron id="18" type="in" activation="linear"/>
<neuron id="19" type="in" activation="linear"/>
<neuron id="20" type="in" activation="linear"/>
<neuron id="21" type="in" activation="linear"/>
<neuron id="22" type="in" activation="linear"/>
<neuron id="23" type="in" activation="linear"/>
<neuron id="24" type="in" activation="linear"/>
<neuron id="25" type="in" activation="linear"/>
<neuron id="26" type="in" activation="linear"/>
<neuron id="27" type="in" activation="linear"/>
<neuron id="28" type="in" activation="linear"/>
<neuron id="29" type="in" activation="linear"/>
<neuron id="30" type="in" activation="linear"/>
<neuron id="31" type="in" activation="linear"/>
<neuron id="32" type="in" activation="linear"/>
<neuron id="33" type="in" activation="linear"/>
<neuron id="34" type="in" activation="linear"/>
<neuron id="35" type="in" activation="linear"/>
<neuron id="36" type="in" activation="linear"/>
<neuron id="37" type="in" activation="linear"/>
<neuron id="38" type="in" activation="linear"/>
<neuron id="39" type="in" activation="linear"/>
<neuron id="40" type="in" activation="linear"/>
<neuron id="41" type="in" activation="linear"/>
<neuron id="42" type="in" activation="linear"/>
<neuron id="43" type="in" activation="linear"/>
<neuron id="44" type="in" activation="linear"/>
<neuron id="45" type="in" activation="linear"/>
<neuron id="46" type="in" activation="linear"/>
<neuron id="47" type="in" activation="linear"/>
<neuron id="48" type="in" activation="linear"/>
<neuron id="49" type="in" activation="linear"/>
<neuron id="50" type="in" activation="linear"/>
<neuron id="51" type="in" activation="linear"/>
<neuron id="52" type="in" activation="linear"/>
<neuron id="53" type="in" activation="linear"/>
<neuron id="54" type="in" activation="linear"/>
<neuron id="55" type="in" activation="linear"/>
<neuron id="56" type="in" activation="linear"/>
<neuron id="57" type="in" activation="linear"/>
<neuron id="58" type="in" activation="linear"/>
<neuron id="59" type="in" activation="linear"/>
<neuron id="60" type="in" activation="linear"/>
<neuron id="61" type="in" activation="linear"/>
<neuron id="62" type="in" activation="linear"/>
<neuron id="63" type="in" activation="linear"/>
<neuron id="64" type="in" activation="linear"/>
<neuron id="65" type="in" activation="linear"/>
<neuron id="66" type="in" activation="linear"/>
<neuron id="67" type="in" activation="linear"/>
<neuron id="68" type="in" activation="linear"/>
<neuron id="69" type="in" activation="linear"/>
<neuron id="70" type="in" activation="linear"/>
<neuron id="71" type="in" activation="linear"/>
<neuron id="72" type="in" activation="linear"/>
<neuron id="73" type="in" activation="linear"/>
<neuron id="74" type="in" activation="linear"/>
<neuron id="75" type="in" activation="linear"/>
<neuron id="76" type="in" activation="linear"/>
<neuron id="77" type="in" activation="linear"/>
<neuron id="78" type="in" activation="linear"/>
<neuron id="79" type="in" activation="linear"/>
<neuron id="80" type="in" activation="linear"/>
<neuron id="81" type="in" activation="linear"/>
<neuron id="82" type="in" activation="linear"/>
<neuron id="83" type="in" activation="linear"/>
<neuron id="84" type="in" activation="linear"/>
<neuron id="85" type="in" activation="linear"/>
<neuron id="86" type="in" activation="linear"/>
<neuron id="87" type="in" activation="linear"/>
<neuron id="88" type="in" activation="linear"/>
<neuron id="89" type="in" activation="linear"/>
<neuron id="90" type="in" activation="linear"/>
<neuron id="91" type="in" activation="linear"/>
<neuron id="92" type="in" activation="linear"/>
<neuron id="93" type="in" activation="linear"/>
<neuron id="94" type="in" activation="linear"/>
<neuron id="95" type="in" activation="linear"/>
<neuron id="96" type="in" activation="linear"/>
<neuron id="97" type="in" activation="linear"/>
<neuron id="98" type="in" activation="linear"/>
<neuron id="99" type="in" activation="linear"/>
<neuron id="100" type="in" activation="linear"/>
<neuron id="101" type="out" activation="sigmoid"/>
<connection id="102" src-id="0" dest-id="101" weight="2.279451819135792"/>
<connection id="103" src-id="1" dest-id="101" weight="0.12869353792408178"/>
<connection id="104" src-id="2" dest-id="101" weight="-1.635479847925502"/>
<connection id="105" src-id="3" dest-id="101" weight="-2.03007414101119"/>
<connection id="106" src-id="4" dest-id="101" weight="-5.22363881587165"/>
<connection id="107" src-id="5" dest-id="101" weight="5.066533183927731"/>
<connection id="108" src-id="6" dest-id="101" weight="1.2429489514787493"/>
<connection id="109" src-id="7" dest-id="101" weight="-2.1243335264288916"/>
<connection id="110" src-id="8" dest-id="101" weight="-2.1723899838287073"/>
<connection id="111" src-id="9" dest-id="101" weight="1.1257859102680339"/>
<connection id="112" src-id="10" dest-id="101" weight="1.1940438194151741"/>
<connection id="113" src-id="11" dest-id="101" weight="-1.1498017184982716"/>
<connection id="114" src-id="12" dest-id="101" weight="0.1319540995382663"/>
<connection id="115" src-id="13" dest-id="101" weight="1.4678772719651225"/>
<connection id="116" src-id="14" dest-id="101" weight="0.39704259943276643"/>
<connection id="117" src-id="15" dest-id="101" weight="0.8438020723722306"/>
<connection id="118" src-id="16" dest-id="101" weight="-0.7308601273476341"/>
<connection id="119" src-id="17" dest-id="101" weight="0.31519753144317564"/>
<connection id="120" src-id="18" dest-id="101" weight="-0.4257895212946432"/>
<connection id="121" src-id="19" dest-id="101" weight="-2.984097399821008"/>
<connection id="122" src-id="20" dest-id="101" weight="-0.4863406889350979"/>
<connection id="123" src-id="21" dest-id="101" weight="1.5044183327283926"/>
<connection id="124" src-id="22" dest-id="101" weight="-0.3805489692149082"/>
<connection id="125" src-id="23" dest-id="101" weight="0.8770567386235719"/>
<connection id="126" src-id="24" dest-id="101" weight="-5.3188059564172"/>
<connection id="127" src-id="25" dest-id="101" weight="4.934724601812862"/>
<connection id="128" src-id="26" dest-id="101" weight="-0.5283772494847097"/>
<connection id="129" src-id="27" dest-id="101" weight="4.229173141071572"/>
<connection id="130" src-id="28" dest-id="101" weight="-1.5711327062478149"/>
<connection id="131" src-id="29" dest-id="101" weight="2.415839036627939"/>
<connection id="132" src-id="30" dest-id="101" weight="-3.8193484486225904"/>
<connection id="133" src-id="31" dest-id="101" weight="1.2905069751476699"/>
<connection id="134" src-id="32" dest-id="101" weight="0.649027046136016"/>
<connection id="135" src-id="33" dest-id="101" weight="0.5436923114268699"/>
<connection id="136" src-id="34" dest-id="101" weight="-5.884475488829776"/>
<connection id="137" src-id="35" dest-id="101" weight="-1.7966728666090992"/>
<connection id="138" src-id="36" dest-id="101" weight="0.7814643037308693"/>
<connection id="139" src-id="37" dest-id="101" weight="1.342509565921345"/>
<connection id="140" src-id="38" dest-id="101" weight="2.971875843858863"/>
<connection id="141" src-id="39" dest-id="101" weight="0.3836752855198615"/>
<connection id="142" src-id="40" dest-id="101" weight="5.373174865245941"/>
<connection id="143" src-id="41" dest-id="101" weight="0.5810087744587444"/>
<connection id="144" src-id="42" dest-id="101" weight="-1.5646685330172336"/>
<connection id="145" src-id="43" dest-id="101" weight="0.9881463944574279"/>
<connection id="146" src-id="44" dest-id="101" weight="-1.9048646624423766"/>
<connection id="147" src-id="45" dest-id="101" weight="0.6265216106867533"/>
<connection id="148" src-id="46" dest-id="101" weight="2.748829350802719"/>
<connection id="149" src-id="47" dest-id="101" weight="-1.2275590106576608"/>
<connection id="150" src-id="48" dest-id="101" weight="0.22200368424313682"/>
<connection id="151" src-id="49" dest-id="101" weight="5.189846303223446"/>
<connection id="152" src-id="50" dest-id="101" weight="0.35510223474417346"/>
<connection id="153" src-id="51" dest-id="101" weight="-4.340028692015827"/>
<connection id="154" src-id="52" dest-id="101" weight="3.5509393341595175"/>
<connection id="155" src-id="53" dest-id="101" weight="-1.2547093966871237"/>
<connection id="156" src-id="54" dest-id="101" weight="1.3835036233133735"/>
<connection id="157" src-id="55" dest-id="101" weight="4.763715648438528"/>
<connection id="158" src-id="56" dest-id="101" weight="-0.10104645229778425"/>
<connection id="159" src-id="57" dest-id="101" weight="1.4261842015502928"/>
<connection id="160" src-id="58" dest-id="101" weight="-2.244665975446747"/>
<connection id="161" src-id="59" dest-id="101" weight="2.7332753543840567"/>
<connection id="162" src-id="60" dest-id="101" weight="-1.6411914554142353"/>
<connection id="163" src-id="61" dest-id="101" weight="0.6266758602645899"/>
<connection id="164" src-id="62" dest-id="101" weight="-2.1587738057508687"/>
<connection id="165" src-id="63" dest-id="101" weight="5.179806369156698"/>
<connection id="166" src-id="64" dest-id="101" weight="-2.8264013677133963"/>
<connection id="167" src-id="65" dest-id="101" weight="-1.5508535984706489"/>
<connection id="168" src-id="66" dest-id="101" weight="-1.053070814790915"/>
<connection id="169" src-id="67" dest-id="101" weight="-2.9634596056490388"/>
<connection id="170" src-id="68" dest-id="101" weight="-0.8475968625108183"/>
<connection id="171" src-id="69" dest-id="101" weight="1.56531938925027"/>
<connection id="172" src-id="70" dest-id="101" weight="2.6024324466626125"/>
<connection id="173" src-id="71" dest-id="101" weight="1.0499845347404693"/>
<connection id="174" src-id="72" dest-id="101" weight="0.3638329023148795"/>
<connection id="175" src-id="73" dest-id="101" weight="-0.03649285549373138"/>
<connection id="176" src-id="74" dest-id="101" weight="1.6575922569253918"/>
<connection id="177" src-id="75" dest-id="101" weight="-0.8742092238128079"/>
<connection id="178" src-id="76" dest-id="101" weight="4.836892893410877"/>
<connection id="179" src-id="77" dest-id="101" weight="-0.8040297457082133"/>
<connection id="180" src-id="78" dest-id="101" weight="1.82696019318446"/>
<connection id="181" src-id="79" dest-id="101" weight="-0.293777268412463"/>
<connection id="182" src-id="80" dest-id="101" weight="-2.9668272909691042"/>
<connection id="183" src-id="81" dest-id="101" weight="-1.309985047819153"/>
<connection id="184" src-id="82" dest-id="101" weight="0.49077994800628194"/>
<connection id="185" src-id="83" dest-id="101" weight="-1.5820712090740512"/>
<connection id="186" src-id="84" dest-id="101" weight="-0.07309802621426253"/>
<connection id="187" src-id="85" dest-id="101" weight="-0.623584476421643"/>
<connection id="188" src-id="86" dest-id="101" weight="2.282146894704152"/>
<connection id="189" src-id="87" dest-id="101" weight="1.0130693170355556"/>
<connection id="190" src-id="88" dest-id="101" weight="-0.6630819217951083"/>
<connection id="191" src-id="89" dest-id="101" weight="-0.6100670515802803"/>
<connection id="192" src-id="90" dest-id="101" weight="0.7274262199578554"/>
<connection id="193" src-id="91" dest-id="101" weight="1.7111287508335757"/>
<connection id="194" src-id="92" dest-id="101" weight="1.7839751284534664"/>
<connection id="195" src-id="93" dest-id="101" weight="3.55407388260916"/>
<connection id="196" src-id="94" dest-id="101" weight="-1.8746506082503458"/>
<connection id="197" src-id="95" dest-id="101" weight="1.8621527996171547"/>
<connection id="198" src-id="96" dest-id="101" weight="0.11135936926449697"/>
<connection id="199" src-id="97" dest-id="101" weight="3.6461788712951"/>
<connection id="200" src-id="98" dest-id="101" weight="1.2284642929564988"/>
<connection id="201" src-id="99" dest-id="101" weight="1.3805338072679203"/>
<connection id="202" src-id="100" dest-id="101" weight="-3.9204980381024748"/>
<neuron id="203" type="out" activation="sigmoid"/>
<connection id="204" src-id="0" dest-id="203" weight="3.8246147708990312"/>
<connection id="205" src-id="1" dest-id="203" weight="1.4653098931415398"/>
<connection id="206" src-id="2" dest-id="203" weight="-3.976291006730384"/>
<connection id="207" src-id="3" dest-id="203" weight="0.1979341421148717"/>
<connection id="208" src-id="4" dest-id="203" weight="-0.976635189431152"/>
<connection id="209" src-id="5" dest-id="203" weight="0.851527290262053"/>
<connection id="210" src-id="6" dest-id="203" weight="0.6974974213868863"/>
<connection id="211" src-id="7" dest-id="203" weight="-1.3990261105386697"/>
<connection id="212" src-id="8" dest-id="203" weight="-1.1555327748908764"/>
<connection id="213" src-id="9" dest-id="203" weight="3.2708696316635106"/>
<connection id="214" src-id="10" dest-id="203" weight="0.953208423394017"/>
<connection id="215" src-id="11" dest-id="203" weight="4.506489597155978"/>
<connection id="216" src-id="12" dest-id="203" weight="0.009970750234893577"/>
<connection id="217" src-id="13" dest-id="203" weight="-0.4717756303587799"/>
<connection id="218" src-id="14" dest-id="203" weight="-0.4263779528056998"/>
<connection id="219" src-id="15" dest-id="203" weight="0.11960283742348787"/>
<connection id="220" src-id="16" dest-id="203" weight="-2.9571251565397016"/>
<connection id="221" src-id="17" dest-id="203" weight="-1.1533508118045042"/>
<connection id="222" src-id="18" dest-id="203" weight="-2.927790207212711"/>
<connection id="223" src-id="19" dest-id="203" weight="5.20478925343553"/>
<connection id="224" src-id="20" dest-id="203" weight="-1.5619358100604679"/>
<connection id="225" src-id="21" dest-id="203" weight="-0.19434676832479258"/>
<connection id="226" src-id="22" dest-id="203" weight="3.988879391128453"/>
<connection id="227" src-id="23" dest-id="203" weight="1.9180735548126127"/>
<connection id="228" src-id="24" dest-id="203" weight="-0.052990707718228114"/>
<connection id="229" src-id="25" dest-id="203" weight="4.453547985691128"/>
<connection id="230" src-id="26" dest-id="203" weight="1.3178376577663506"/>
<connection id="232" src-id="28" dest-id="203" weight="1.2881092160437362"/>
<connection id="233" src-id="29" dest-id="203" weight="4.385535847894421"/>
<connection id="234" src-id="30" dest-id="203" weight="0.25165496790168607"/>
<connection id="235" src-id="31" dest-id="203" weight="0.6323340465213597"/>
<connection id="236" src-id="32" dest-id="203" weight="0.7880403121514024"/>
<connection id="237" src-id="33" dest-id="203" weight="-2.385040017365686"/>
<connection id="238" src-id="34" dest-id="203" weight="0.9964895811864698"/>
<connection id="239" src-id="35" dest-id="203" weight="0.9039152852058027"/>
<connection id="240" src-id="36" dest-id="203" weight="-0.890492449036858"/>
<connection id="241" src-id="37" dest-id="203" weight="-1.233776885382036"/>
<connection id="242" src-id="38" dest-id="203" weight="4.095785772104575"/>
<connection id="243" src-id="39" dest-id="203" weight="-2.1131107835292533"/>
<connection id="244" src-id="40" dest-id="203" weight="-0.22510558814868475"/>
<connection id="245" src-id="41" dest-id="203" weight="1.3042224049304902"/>
<connection id="246" src-id="42" dest-id="203" weight="-1.8732554398030736"/>
<connection id="247" src-id="43" dest-id="203" weight="-1.1297698593541694"/>
<connection id="248" src-id="44" dest-id="203" weight="0.35452403078738115"/>
<connection id="249" src-id="45" dest-id="203" weight="1.8021615242693128"/>
<connection id="250" src-id="46" dest-id="203" weight="0.17638666038450712"/>
<connection id="251" src-id="47" dest-id="203" weight="2.4240080434033446"/>
<connection id="252" src-id="48" dest-id="203" weight="2.580591740789141"/>
<connection id="253" src-id="49" dest-id="203" weight="1.2380848325892782"/>
<connection id="254" src-id="50" dest-id="203" weight="1.856134188655639"/>
<connection id="255" src-id="51" dest-id="203" weight="-0.2679147720336914"/>
<connection id="256" src-id="52" dest-id="203" weight="1.9137319537303574"/>
<connection id="257" src-id="53" dest-id="203" weight="-2.210504706616568"/>
<connection id="258" src-id="54" dest-id="203" weight="-1.6971930562884765"/>
<connection id="259" src-id="55" dest-id="203" weight="-6.172703672852707"/>
<connection id="260" src-id="56" dest-id="203" weight="-1.9721715988897748"/>
<connection id="261" src-id="57" dest-id="203" weight="-0.05667795056234004"/>
<connection id="262" src-id="58" dest-id="203" weight="-1.5675353647335124"/>
<connection id="263" src-id="59" dest-id="203" weight="-2.0211831733514654"/>
<connection id="264" src-id="60" dest-id="203" weight="-2.1556838932542703"/>
<connection id="265" src-id="61" dest-id="203" weight="0.22540645367695444"/>
<connection id="266" src-id="62" dest-id="203" weight="3.9146438898247506"/>
<connection id="267" src-id="63" dest-id="203" weight="-1.231519022175723"/>
<connection id="268" src-id="64" dest-id="203" weight="-2.048214491599037"/>
<connection id="269" src-id="65" dest-id="203" weight="4.159891700575384"/>
<connection id="270" src-id="66" dest-id="203" weight="0.5918658863659105"/>
<connection id="271" src-id="67" dest-id="203" weight="-0.7896136782227892"/>
<connection id="272" src-id="68" dest-id="203" weight="2.8985780759901605"/>
<connection id="273" src-id="69" dest-id="203" weight="0.9228954315185547"/>
<connection id="274" src-id="70" dest-id="203" weight="1.881415731081288"/>
<connection id="275" src-id="71" dest-id="203" weight="1.878831748141197"/>
<connection id="276" src-id="72" dest-id="203" weight="1.260954577527274"/>
<connection id="277" src-id="73" dest-id="203" weight="2.485872140330879"/>
<connection id="278" src-id="74" dest-id="203" weight="-0.2977967151858424"/>
<connection id="279" src-id="75" dest-id="203" weight="-0.20444359814558588"/>
<connection id="280" src-id="76" dest-id="203" weight="-1.3679320218897943"/>
<connection id="281" src-id="77" dest-id="203" weight="1.1139259626290468"/>
<connection id="282" src-id="78" dest-id="203" weight="0.6222141261031631"/>
<connection id="283" src-id="79" dest-id="203" weight="1.0929352403995831"/>
<connection id="284" src-id="80" dest-id="203" weight="-2.111842392003289"/>
<connection id="285" src-id="81" dest-id="203" weight="2.584210252750628"/>
<connection id="286" src-id="82" dest-id="203" weight="0.596014493180997"/>
<connection id="287" src-id="83" dest-id="203" weight="-1.8637795148188223"/>
<connection id="288" src-id="84" dest-id="203" weight="0.3036276284531705"/>
<connection id="289" src-id="85" dest-id="203" weight="-1.1589598176833737"/>
<connection id="290" src-id="86" dest-id="203" weight="0.8882825065900825"/>
<connection id="291" src-id="87" dest-id="203" weight="-2.4070478339599157"/>
<connection id="292" src-id="88" dest-id="203" weight="-2.1335856674729614"/>
<connection id="293" src-id="89" dest-id="203" weight="1.852767008617073"/>
<connection id="294" src-id="90" dest-id="203" weight="0.6130529088113641"/>
<connection id="295" src-id="91" dest-id="203" weight="-0.3919351800486732"/>
<connection id="296" src-id="92" dest-id="203" weight="0.8546950359383266"/>
<connection id="297" src-id="93" dest-id="203" weight="0.8724116405571434"/>
<connection id="298" src-id="94" dest-id="203" weight="-1.9446732423734008"/>
<connection id="299" src-id="95" dest-id="203" weight="1.5758079533480085"/>
<connection id="300" src-id="96" dest-id="203" weight="-1.214695463565099"/>
<connection id="301" src-id="97" dest-id="203" weight="0.19928871772646883"/>
<connection id="302" src-id="98" dest-id="203" weight="2.1838490201404257"/>
<connection id="304" src-id="100" dest-id="203" weight="1.1398227852675666"/>
<neuron id="305" type="out" activation="sigmoid"/>
<connection id="306" src-id="0" dest-id="305" weight="0.7680696183314233"/>
<connection id="307" src-id="1" dest-id="305" weight="-4.5918089816682635"/>
<connection id="308" src-id="2" dest-id="305" weight="0.11081392127734913"/>
<connection id="309" src-id="3" dest-id="305" weight="0.7069726093500797"/>
<connection id="310" src-id="4" dest-id="305" weight="3.1534016416997925"/>
<connection id="311" src-id="5" dest-id="305" weight="-2.8685815972987307"/>
<connection id="312" src-id="6" dest-id="305" weight="-0.3900366310273561"/>
<connection id="313" src-id="7" dest-id="305" weight="1.4995420148523309"/>
<connection id="314" src-id="8" dest-id="305" weight="0.9653664814229226"/>
<connection id="315" src-id="9" dest-id="305" weight="-0.37286976834289254"/>
<connection id="316" src-id="10" dest-id="305" weight="-2.7863536430594973"/>
<connection id="317" src-id="11" dest-id="305" weight="4.6844279323299345"/>
<connection id="318" src-id="12" dest-id="305" weight="-1.067800174431698"/>
<connection id="319" src-id="13" dest-id="305" weight="-0.6293249785123243"/>
<connection id="320" src-id="14" dest-id="305" weight="0.12377794618715088"/>
<connection id="321" src-id="15" dest-id="305" weight="-0.9118148230211153"/>
<connection id="322" src-id="16" dest-id="305" weight="-3.2128517959785947"/>
<connection id="323" src-id="17" dest-id="305" weight="-5.344458798134964"/>
<connection id="324" src-id="18" dest-id="305" weight="-1.8021896850322179"/>
<connection id="325" src-id="19" dest-id="305" weight="-0.8807560070112042"/>
<connection id="326" src-id="20" dest-id="305" weight="-1.9006052420194304"/>
<connection id="327" src-id="21" dest-id="305" weight="0.874041151607184"/>
<connection id="328" src-id="22" dest-id="305" weight="-4.590183279208469"/>
<connection id="329" src-id="23" dest-id="305" weight="-2.819950298196013"/>
<connection id="330" src-id="24" dest-id="305" weight="-4.853282941040307"/>
<connection id="331" src-id="25" dest-id="305" weight="0.28132818941655113"/>
<connection id="332" src-id="26" dest-id="305" weight="-1.2547161087905623"/>
<connection id="333" src-id="27" dest-id="305" weight="-3.2647876858572378"/>
<connection id="334" src-id="28" dest-id="305" weight="-3.2603302572952795"/>
<connection id="335" src-id="29" dest-id="305" weight="0.7739868593161481"/>
<connection id="336" src-id="30" dest-id="305" weight="-5.236834296592965"/>
<connection id="337" src-id="31" dest-id="305" weight="1.9909169923802066"/>
<connection id="338" src-id="32" dest-id="305" weight="-0.09579500223224291"/>
<connection id="339" src-id="33" dest-id="305" weight="-6.2076066929617"/>
<connection id="340" src-id="34" dest-id="305" weight="1.4694602996103838"/>
<connection id="341" src-id="35" dest-id="305" weight="0.9246390299596695"/>
<connection id="342" src-id="36" dest-id="305" weight="-3.027691151678142"/>
<connection id="343" src-id="37" dest-id="305" weight="-3.7914090767322173"/>
<connection id="344" src-id="38" dest-id="305" weight="0.059327401250185874"/>
<connection id="345" src-id="39" dest-id="305" weight="-2.4387181390092536"/>
<connection id="346" src-id="40" dest-id="305" weight="3.050441293180602"/>
<connection id="347" src-id="41" dest-id="305" weight="2.9756919482844566"/>
<connection id="348" src-id="42" dest-id="305" weight="2.1281428151398614"/>
<connection id="349" src-id="43" dest-id="305" weight="-0.9384030103683472"/>
<connection id="350" src-id="44" dest-id="305" weight="1.3786936170125468"/>
<connection id="351" src-id="45" dest-id="305" weight="4.049206724583896"/>
<connection id="352" src-id="46" dest-id="305" weight="-4.466700616478332"/>
<connection id="353" src-id="47" dest-id="305" weight="1.0384647264359301"/>
<connection id="354" src-id="48" dest-id="305" weight="1.4598799768690998"/>
<connection id="355" src-id="49" dest-id="305" weight="2.691831055568925"/>
<connection id="356" src-id="50" dest-id="305" weight="-2.043948627259622"/>
<connection id="357" src-id="51" dest-id="305" weight="-0.6783899764503205"/>
<connection id="358" src-id="52" dest-id="305" weight="-3.342309216317137"/>
<connection id="359" src-id="53" dest-id="305" weight="-2.8707650728279246"/>
<connection id="360" src-id="54" dest-id="305" weight="-0.7912379736032938"/>
<connection id="361" src-id="55" dest-id="305" weight="1.9544557728684784"/>
<connection id="362" src-id="56" dest-id="305" weight="-2.4987608490929096"/>
<connection id="363" src-id="57" dest-id="305" weight="3.410304706123589"/>
<connection id="364" src-id="58" dest-id="305" weight="0.4986151893505052"/>
<connection id="365" src-id="59" dest-id="305" weight="0.27218751138846886"/>
<connection id="366" src-id="60" dest-id="305" weight="1.8749843493734257"/>
<connection id="367" src-id="61" dest-id="305" weight="-3.645816964228522"/>
<connection id="368" src-id="62" dest-id="305" weight="3.5479027888316184"/>
<connection id="369" src-id="63" dest-id="305" weight="0.31135853602894636"/>
<connection id="370" src-id="64" dest-id="305" weight="-1.0696952757341065"/>
<connection id="371" src-id="65" dest-id="305" weight="2.6796504654085744"/>
<connection id="372" src-id="66" dest-id="305" weight="-1.0752831591360081"/>
<connection id="373" src-id="67" dest-id="305" weight="-0.004411734694827585"/>
<connection id="374" src-id="68" dest-id="305" weight="2.594795426667071"/>
<connection id="375" src-id="69" dest-id="305" weight="-4.104332349404635"/>
<connection id="376" src-id="70" dest-id="305" weight="0.03233239601513154"/>
<connection id="377" src-id="71" dest-id="305" weight="0.2579595173624136"/>
<connection id="378" src-id="72" dest-id="305" weight="-2.609251056873108"/>
<connection id="379" src-id="73" dest-id="305" weight="-1.2037683793700973"/>
<connection id="380" src-id="74" dest-id="305" weight="1.215801724363086"/>
<connection id="381" src-id="75" dest-id="305" weight="-2.3888148253512034"/>
<connection id="382" src-id="76" dest-id="305" weight="0.8085884674054757"/>
<connection id="383" src-id="77" dest-id="305" weight="3.087756712461445"/>
<connection id="384" src-id="78" dest-id="305" weight="-0.20670950412750244"/>
<connection id="385" src-id="79" dest-id="305" weight="0.830572247505188"/>
<connection id="386" src-id="80" dest-id="305" weight="-0.1074596344489448"/>
<connection id="387" src-id="81" dest-id="305" weight="2.4899833421379878"/>
<connection id="388" src-id="82" dest-id="305" weight="1.7960671980350529"/>
<connection id="389" src-id="83" dest-id="305" weight="-1.6519855622815187"/>
<connection id="390" src-id="84" dest-id="305" weight="-3.312836963808605"/>
<connection id="391" src-id="85" dest-id="305" weight="2.0390972966634022"/>
<connection id="392" src-id="86" dest-id="305" weight="1.3819222770865667"/>
<connection id="393" src-id="87" dest-id="305" weight="-4.504035122707663"/>
<connection id="394" src-id="88" dest-id="305" weight="0.20244565799508185"/>
<connection id="395" src-id="89" dest-id="305" weight="-2.135551780658126"/>
<connection id="396" src-id="90" dest-id="305" weight="-2.420460835456587"/>
<connection id="397" src-id="91" dest-id="305" weight="1.2006767355449999"/>
<connection id="398" src-id="92" dest-id="305" weight="0.6203972191071639"/>
<connection id="399" src-id="93" dest-id="305" weight="1.5381745204974009"/>
<connection id="400" src-id="94" dest-id="305" weight="2.7742354944637913"/>
<connection id="401" src-id="95" dest-id="305" weight="-1.8309748156950516"/>
<connection id="403" src-id="97" dest-id="305" weight="-1.5767725567896091"/>
<connection id="404" src-id="98" dest-id="305" weight="3.9618459513411093"/>
<connection id="405" src-id="99" dest-id="305" weight="0.6692449796598845"/>
<connection id="406" src-id="100" dest-id="305" weight="2.2586037720167504"/>
<neuron id="407" type="out" activation="sigmoid"/>
<connection id="408" src-id="0" dest-id="407" weight="-0.12056846118826908"/>
<connection id="409" src-id="1" dest-id="407" weight="0.3604559898376465"/>
<connection id="410" src-id="2" dest-id="407" weight="0.6770557461733258"/>
<connection id="411" src-id="3" dest-id="407" weight="3.2913168723401167"/>
<connection id="412" src-id="4" dest-id="407" weight="-2.047130393024471"/>
<connection id="413" src-id="5" dest-id="407" weight="0.7682932728211727"/>
<connection id="414" src-id="6" dest-id="407" weight="1.4947062095163344"/>
<connection id="415" src-id="7" dest-id="407" weight="2.0500569427577573"/>
<connection id="416" src-id="8" dest-id="407" weight="1.1746096567908317"/>
<connection id="417" src-id="9" dest-id="407" weight="1.094312694447437"/>
<connection id="418" src-id="10" dest-id="407" weight="0.9689684933026468"/>
<connection id="419" src-id="11" dest-id="407" weight="1.1548286364521068"/>
<connection id="420" src-id="12" dest-id="407" weight="3.9244158725948193"/>
<connection id="421" src-id="13" dest-id="407" weight="-0.9031774711005057"/>
<connection id="422" src-id="14" dest-id="407" weight="0.0870826244354248"/>
<connection id="423" src-id="15" dest-id="407" weight="3.2390967107177953"/>
<connection id="424" src-id="16" dest-id="407" weight="-3.3601306231531396"/>
<connection id="425" src-id="17" dest-id="407" weight="-0.6188068428609029"/>
<connection id="426" src-id="18" dest-id="407" weight="-1.9905741061021471"/>
<connection id="427" src-id="19" dest-id="407" weight="0.6115259193285718"/>
<connection id="428" src-id="20" dest-id="407" weight="-3.1081509850196487"/>
<connection id="429" src-id="21" dest-id="407" weight="-1.268618874227869"/>
<connection id="430" src-id="22" dest-id="407" weight="2.1120173388320236"/>
<connection id="431" src-id="23" dest-id="407" weight="3.447354091151326"/>
<connection id="432" src-id="24" dest-id="407" weight="-1.5173961763903048"/>
<connection id="433" src-id="25" dest-id="407" weight="-1.167233345778619"/>
<connection id="434" src-id="26" dest-id="407" weight="-0.8525255918502808"/>
<connection id="435" src-id="27" dest-id="407" weight="2.085349219123284"/>
<connection id="436" src-id="28" dest-id="407" weight="2.328985219638004"/>
<connection id="437" src-id="29" dest-id="407" weight="0.07621967313345468"/>
<connection id="438" src-id="30" dest-id="407" weight="-0.4753241962215058"/>
<connection id="439" src-id="31" dest-id="407" weight="-0.49221883224875873"/>
<connection id="440" src-id="32" dest-id="407" weight="1.6997294196912827"/>
<connection id="441" src-id="33" dest-id="407" weight="4.164717994398964"/>
<connection id="442" src-id="34" dest-id="407" weight="1.6667859906095028"/>
<connection id="443" src-id="35" dest-id="407" weight="2.200804522161345"/>
<connection id="444" src-id="36" dest-id="407" weight="-0.2327905461509423"/>
<connection id="445" src-id="37" dest-id="407" weight="-1.2662955278309336"/>
<connection id="446" src-id="38" dest-id="407" weight="-2.566739873411667"/>
<connection id="447" src-id="39" dest-id="407" weight="-0.08835885458002357"/>
<connection id="448" src-id="40" dest-id="407" weight="2.2182399399853145"/>
<connection id="449" src-id="41" dest-id="407" weight="-2.0603572638709586"/>
<connection id="450" src-id="42" dest-id="407" weight="-2.258338386300435"/>
<connection id="451" src-id="43" dest-id="407" weight="1.0088246982352058"/>
<connection id="452" src-id="44" dest-id="407" weight="-1.7822384915501677"/>
<connection id="453" src-id="45" dest-id="407" weight="-0.038671014385264935"/>
<connection id="454" src-id="46" dest-id="407" weight="1.0351649629700863"/>
<connection id="455" src-id="47" dest-id="407" weight="4.9569870433826715"/>
<connection id="456" src-id="48" dest-id="407" weight="-0.28237068121203657"/>
<connection id="457" src-id="49" dest-id="407" weight="0.06774522376004599"/>
<connection id="458" src-id="50" dest-id="407" weight="-0.8924910132534306"/>
<connection id="459" src-id="51" dest-id="407" weight="0.5416886912320795"/>
<connection id="460" src-id="52" dest-id="407" weight="1.393471418837736"/>
<connection id="461" src-id="53" dest-id="407" weight="-2.4731355477798163"/>
<connection id="462" src-id="54" dest-id="407" weight="1.9470276522905645"/>
<connection id="463" src-id="55" dest-id="407" weight="-0.4416560541955854"/>
<connection id="464" src-id="56" dest-id="407" weight="-1.8513773106330125"/>
<connection id="465" src-id="57" dest-id="407" weight="4.361671718843312"/>
<connection id="466" src-id="58" dest-id="407" weight="1.4735096081081593"/>
<connection id="467" src-id="59" dest-id="407" weight="1.3026153026343803"/>
<connection id="468" src-id="60" dest-id="407" weight="3.7278018177667476"/>
<connection id="469" src-id="61" dest-id="407" weight="-1.0285804708977804"/>
<connection id="470" src-id="62" dest-id="407" weight="0.8792861424103426"/>
<connection id="471" src-id="63" dest-id="407" weight="-0.9363692640366547"/>
<connection id="472" src-id="64" dest-id="407" weight="-0.14451775071588058"/>
<connection id="473" src-id="65" dest-id="407" weight="-2.2583547996784055"/>
<connection id="474" src-id="66" dest-id="407" weight="-1.1502685392032252"/>
<connection id="475" src-id="67" dest-id="407" weight="0.24719278702005143"/>
<connection id="476" src-id="68" dest-id="407" weight="-1.1522163422301999"/>
<connection id="477" src-id="69" dest-id="407" weight="-0.4838296557439654"/>
<connection id="478" src-id="70" dest-id="407" weight="0.9052299821060229"/>
<connection id="479" src-id="71" dest-id="407" weight="0.18940299467954358"/>
<connection id="480" src-id="72" dest-id="407" weight="-0.3735053714109696"/>
<connection id="482" src-id="74" dest-id="407" weight="-1.265559367207243"/>
<connection id="483" src-id="75" dest-id="407" weight="1.9165550314233575"/>
<connection id="484" src-id="76" dest-id="407" weight="3.9855915748767368"/>
<connection id="485" src-id="77" dest-id="407" weight="0.8578315994775738"/>
<connection id="486" src-id="78" dest-id="407" weight="-2.0478895603144385"/>
<connection id="487" src-id="79" dest-id="407" weight="-0.6731756108091127"/>
<connection id="488" src-id="80" dest-id="407" weight="1.0097045096294455"/>
<connection id="489" src-id="81" dest-id="407" weight="-2.0579423359303872"/>
<connection id="490" src-id="82" dest-id="407" weight="-0.003216031656163576"/>
<connection id="491" src-id="83" dest-id="407" weight="1.0334163351965446"/>
<connection id="492" src-id="84" dest-id="407" weight="-0.22848963898361907"/>
<connection id="493" src-id="85" dest-id="407" weight="2.5334984388719684"/>
<connection id="494" src-id="86" dest-id="407" weight="0.15252916131793004"/>
<connection id="495" src-id="87" dest-id="407" weight="-1.3498084134625543"/>
<connection id="496" src-id="88" dest-id="407" weight="-1.8951562362320595"/>
<connection id="497" src-id="89" dest-id="407" weight="-0.008955605804921246"/>
<connection id="498" src-id="90" dest-id="407" weight="-2.2045605831982495"/>
<connection id="499" src-id="91" dest-id="407" weight="-2.2326548718835397"/>
<connection id="500" src-id="92" dest-id="407" weight="3.7508857113595715"/>
<connection id="501" src-id="93" dest-id="407" weight="-2.5901364176622637"/>
<connection id="502" src-id="94" dest-id="407" weight="-1.515874381575164"/>
<connection id="503" src-id="95" dest-id="407" weight="-3.2251349546866455"/>
<connection id="504" src-id="96" dest-id="407" weight="1.0935200005053674"/>
<connection id="505" src-id="97" dest-id="407" weight="1.0106092914578746"/>
<connection id="506" src-id="98" dest-id="407" weight="0.7153915551385359"/>
<connection id="507" src-id="99" dest-id="407" weight="-0.26812323072144784"/>
<connection id="508" src-id="100" dest-id="407" weight="-3.1904760921253663"/>
<neuron id="509" type="out" activation="sigmoid"/>
<connection id="510" src-id="0" dest-id="509" weight="1.4399913062813554"/>
<connection id="511" src-id="1" dest-id="509" weight="2.846505251102207"/>
<connection id="512" src-id="2" dest-id="509" weight="-1.2602096028951437"/>
<connection id="513" src-id="3" dest-id="509" weight="-2.955470781196876"/>
<connection id="514" src-id="4" dest-id="509" weight="2.4683640912356233"/>
<connection id="515" src-id="5" dest-id="509" weight="-0.06607627785976761"/>
<connection id="516" src-id="6" dest-id="509" weight="-5.339160252873364"/>
<connection id="517" src-id="7" dest-id="509" weight="-1.0421518933836886"/>
<connection id="518" src-id="8" dest-id="509" weight="4.2119362703941885"/>
<connection id="519" src-id="9" dest-id="509" weight="-0.44200327523261707"/>
<connection id="520" src-id="10" dest-id="509" weight="0.13488370244135867"/>
<connection id="521" src-id="11" dest-id="509" weight="-2.8479545730983444"/>
<connection id="522" src-id="12" dest-id="509" weight="2.453045171140053"/>
<connection id="523" src-id="13" dest-id="509" weight="2.403785785851424"/>
<connection id="524" src-id="14" dest-id="509" weight="-2.1346208027698856"/>
<connection id="525" src-id="15" dest-id="509" weight="4.093004407518825"/>
<connection id="526" src-id="16" dest-id="509" weight="-3.288869702913933"/>
<connection id="527" src-id="17" dest-id="509" weight="0.7062246580950822"/>
<connection id="528" src-id="18" dest-id="509" weight="-1.7045524898468365"/>
<connection id="529" src-id="19" dest-id="509" weight="-1.1806161734815366"/>
<connection id="530" src-id="20" dest-id="509" weight="1.5192855192832695"/>
<connection id="531" src-id="21" dest-id="509" weight="-0.6924727062043416"/>
<connection id="532" src-id="22" dest-id="509" weight="4.44399966755733"/>
<connection id="533" src-id="23" dest-id="509" weight="4.075797273979381"/>
<connection id="534" src-id="24" dest-id="509" weight="-3.2268899568632046"/>
<connection id="535" src-id="25" dest-id="509" weight="-1.4635126220955323"/>
<connection id="536" src-id="26" dest-id="509" weight="-0.7235590884930931"/>
<connection id="537" src-id="27" dest-id="509" weight="0.18565408561013896"/>
<connection id="538" src-id="28" dest-id="509" weight="0.8808762505121999"/>
<connection id="539" src-id="29" dest-id="509" weight="1.2666370999827072"/>
<connection id="540" src-id="30" dest-id="509" weight="-1.8393450194735639"/>
<connection id="541" src-id="31" dest-id="509" weight="-4.923191899020701"/>
<connection id="542" src-id="32" dest-id="509" weight="0.4312966193761696"/>
<connection id="543" src-id="33" dest-id="509" weight="-1.6960822519478218"/>
<connection id="544" src-id="34" dest-id="509" weight="0.7205805798840242"/>
<connection id="545" src-id="35" dest-id="509" weight="2.5504702735545948"/>
<connection id="546" src-id="36" dest-id="509" weight="0.05253145946799109"/>
<connection id="547" src-id="37" dest-id="509" weight="-3.210984113528191"/>
<connection id="548" src-id="38" dest-id="509" weight="1.0059998674055748"/>
<connection id="549" src-id="39" dest-id="509" weight="-1.1710038390850306"/>
<connection id="550" src-id="40" dest-id="509" weight="-3.2327408087441407"/>
<connection id="551" src-id="41" dest-id="509" weight="1.534507921180408"/>
<connection id="552" src-id="42" dest-id="509" weight="2.334663414761351"/>
<connection id="553" src-id="43" dest-id="509" weight="2.015922804360631"/>
<connection id="554" src-id="44" dest-id="509" weight="2.4946234500633198"/>
<connection id="555" src-id="45" dest-id="509" weight="-1.6255281574021585"/>
<connection id="556" src-id="46" dest-id="509" weight="2.5931736749694014"/>
<connection id="557" src-id="47" dest-id="509" weight="-0.8116377735100861"/>
<connection id="558" src-id="48" dest-id="509" weight="1.156350562781054"/>
<connection id="559" src-id="49" dest-id="509" weight="-0.005150186114118077"/>
<connection id="561" src-id="51" dest-id="509" weight="-1.2267498550854616"/>
<connection id="562" src-id="52" dest-id="509" weight="3.373282227194726"/>
<connection id="563" src-id="53" dest-id="509" weight="-4.797692377006599"/>
<connection id="564" src-id="54" dest-id="509" weight="5.3090977499908805"/>
<connection id="565" src-id="55" dest-id="509" weight="4.287697258135257"/>
<connection id="566" src-id="56" dest-id="509" weight="-1.8842940662009633"/>
<connection id="567" src-id="57" dest-id="509" weight="2.6284765827667647"/>
<connection id="568" src-id="58" dest-id="509" weight="-1.1080336083401139"/>
<connection id="569" src-id="59" dest-id="509" weight="-2.2248229545982197"/>
<connection id="570" src-id="60" dest-id="509" weight="0.5669848650382652"/>
<connection id="571" src-id="61" dest-id="509" weight="1.6914422860551666"/>
<connection id="572" src-id="62" dest-id="509" weight="0.4667678795953297"/>
<connection id="573" src-id="63" dest-id="509" weight="-0.9815964009213596"/>
<connection id="574" src-id="64" dest-id="509" weight="5.056169194385288"/>
<connection id="575" src-id="65" dest-id="509" weight="0.3489840209332543"/>
<connection id="576" src-id="66" dest-id="509" weight="-0.7293749532162784"/>
<connection id="577" src-id="67" dest-id="509" weight="5.837471142457494"/>
<connection id="578" src-id="68" dest-id="509" weight="3.3496969444598905"/>
<connection id="579" src-id="69" dest-id="509" weight="3.8804599646566067"/>
<connection id="580" src-id="70" dest-id="509" weight="0.8798701988590575"/>
<connection id="581" src-id="71" dest-id="509" weight="-4.065371108296375"/>
<connection id="582" src-id="72" dest-id="509" weight="-1.2406944554564618"/>
<connection id="583" src-id="73" dest-id="509" weight="-0.42344939708709717"/>
<connection id="584" src-id="74" dest-id="509" weight="-0.09931571982794729"/>
<connection id="585" src-id="75" dest-id="509" weight="1.4125350211209835"/>
<connection id="586" src-id="76" dest-id="509" weight="1.0000676589896498"/>
<connection id="587" src-id="77" dest-id="509" weight="1.0936789268676592"/>
<connection id="588" src-id="78" dest-id="509" weight="3.342924943582735"/>
<connection id="589" src-id="79" dest-id="509" weight="3.3361717283099415"/>
<connection id="590" src-id="80" dest-id="509" weight="-1.5286100126878872"/>
<connection id="591" src-id="81" dest-id="509" weight="1.8106547691755301"/>
<connection id="592" src-id="82" dest-id="509" weight="-5.3317305398860135"/>
<connection id="593" src-id="83" dest-id="509" weight="-3.0601845927181275"/>
<connection id="594" src-id="84" dest-id="509" weight="-0.8508992195129395"/>
<connection id="595" src-id="85" dest-id="509" weight="-0.4724216938722464"/>
<connection id="596" src-id="86" dest-id="509" weight="-1.2994918804602817"/>
<connection id="597" src-id="87" dest-id="509" weight="0.9139081357297365"/>
<connection id="598" src-id="88" dest-id="509" weight="3.331405562295479"/>
<connection id="599" src-id="89" dest-id="509" weight="7.0659404450307175"/>
<connection id="600" src-id="90" dest-id="509" weight="4.224530984677553"/>
<connection id="601" src-id="91" dest-id="509" weight="0.5333752136841285"/>
<connection id="602" src-id="92" dest-id="509" weight="-1.227897754375702"/>
<connection id="603" src-id="93" dest-id="509" weight="-1.6231891595130228"/>
<connection id="604" src-id="94" dest-id="509" weight="0.2779541837713714"/>
<connection id="605" src-id="95" dest-id="509" weight="0.7427335977554321"/>
<connection id="606" src-id="96" dest-id="509" weight="0.20448328318025633"/>
<connection id="607" src-id="97" dest-id="509" weight="-0.021994296634918697"/>
<connection id="608" src-id="98" dest-id="509" weight="-4.093702549670734"/>
<connection id="610" src-id="100" dest-id="509" weight="-0.28943792700713145"/>
<neuron id="611" type="out" activation="sigmoid"/>
<connection id="612" src-id="0" dest-id="611" weight="-3.0805046513913044"/>
<connection id="613" src-id="1" dest-id="611" weight="-0.39883045016982677"/>
<connection id="614" src-id="2" dest-id="611" weight="-2.7830228798873096"/>
<connection id="615" src-id="3" dest-id="611" weight="-3.5065618774737484"/>
<connection id="616" src-id="4" dest-id="611" weight="-1.1731796739667857"/>
<connection id="617" src-id="5" dest-id="611" weight="5.708243583332033"/>
<connection id="618" src-id="6" dest-id="611" weight="1.3058199093137972"/>
<connection id="619" src-id="7" dest-id="611" weight="-0.2224974870134384"/>
<connection id="620" src-id="8" dest-id="611" weight="-2.26557184303045"/>
<connection id="621" src-id="9" dest-id="611" weight="0.7460756187926882"/>
<connection id="622" src-id="10" dest-id="611" weight="0.7877060500661206"/>
<connection id="623" src-id="11" dest-id="611" weight="-0.7906760399311498"/>
<connection id="624" src-id="12" dest-id="611" weight="-0.9610605419239362"/>
<connection id="625" src-id="13" dest-id="611" weight="2.3516118283397733"/>
<connection id="626" src-id="14" dest-id="611" weight="0.7222635151642707"/>
<connection id="627" src-id="15" dest-id="611" weight="-0.7822821445145975"/>
<connection id="628" src-id="16" dest-id="611" weight="2.015481993311405"/>
<connection id="629" src-id="17" dest-id="611" weight="-1.9128295952439012"/>
<connection id="630" src-id="18" dest-id="611" weight="2.0075234185381836"/>
<connection id="631" src-id="19" dest-id="611" weight="0.3587845416415748"/>
<connection id="632" src-id="20" dest-id="611" weight="0.924054286678947"/>
<connection id="633" src-id="21" dest-id="611" weight="0.6342164278030396"/>
<connection id="634" src-id="22" dest-id="611" weight="0.4351164734128914"/>
<connection id="635" src-id="23" dest-id="611" weight="5.42638693942044"/>
<connection id="636" src-id="24" dest-id="611" weight="0.5354019645759724"/>
<connection id="637" src-id="25" dest-id="611" weight="-0.3153583494097435"/>
<connection id="638" src-id="26" dest-id="611" weight="1.1992895267049033"/>
<connection id="639" src-id="27" dest-id="611" weight="1.5609757889849076"/>
<connection id="640" src-id="28" dest-id="611" weight="0.7554325343070261"/>
<connection id="641" src-id="29" dest-id="611" weight="1.0862519800293933"/>
<connection id="642" src-id="30" dest-id="611" weight="2.693633376746233"/>
<connection id="643" src-id="31" dest-id="611" weight="1.9053158520134401"/>
<connection id="644" src-id="32" dest-id="611" weight="1.3467710238596373"/>
<connection id="645" src-id="33" dest-id="611" weight="3.1480024591803644"/>
<connection id="646" src-id="34" dest-id="611" weight="2.860532620609323"/>
<connection id="647" src-id="35" dest-id="611" weight="-0.22362438752434954"/>
<connection id="648" src-id="36" dest-id="611" weight="-5.785460030618194"/>
<connection id="649" src-id="37" dest-id="611" weight="-1.2263239510928732"/>
<connection id="650" src-id="38" dest-id="611" weight="2.902267042746042"/>
<connection id="651" src-id="39" dest-id="611" weight="-0.5409489046349024"/>
<connection id="652" src-id="40" dest-id="611" weight="-0.12057394487158485"/>
<connection id="653" src-id="41" dest-id="611" weight="-4.670642436831813"/>
<connection id="654" src-id="42" dest-id="611" weight="-0.2297047595267876"/>
<connection id="655" src-id="43" dest-id="611" weight="-0.6235557529652814"/>
<connection id="656" src-id="44" dest-id="611" weight="-1.0002302436539647"/>
<connection id="657" src-id="45" dest-id="611" weight="-2.4445373677701205"/>
<connection id="658" src-id="46" dest-id="611" weight="3.3126782779764703"/>
<connection id="659" src-id="47" dest-id="611" weight="0.524279206312371"/>
<connection id="660" src-id="48" dest-id="611" weight="-0.5681848692185455"/>
<connection id="661" src-id="49" dest-id="611" weight="-3.4349358799402427"/>
<connection id="662" src-id="50" dest-id="611" weight="0.488087635232337"/>
<connection id="663" src-id="51" dest-id="611" weight="-0.479374108639842"/>
<connection id="664" src-id="52" dest-id="611" weight="-1.4032217825153097"/>
<connection id="665" src-id="53" dest-id="611" weight="1.9768960559656872"/>
<connection id="666" src-id="54" dest-id="611" weight="-0.6006526947021484"/>
<connection id="667" src-id="55" dest-id="611" weight="0.7132292677049028"/>
<connection id="668" src-id="56" dest-id="611" weight="-4.598736878576599"/>
<connection id="669" src-id="57" dest-id="611" weight="-2.2861680683892662"/>
<connection id="670" src-id="58" dest-id="611" weight="-3.7796593969543224"/>
<connection id="671" src-id="59" dest-id="611" weight="0.7892868864030906"/>
<connection id="672" src-id="60" dest-id="611" weight="-4.670807260252038"/>
<connection id="673" src-id="61" dest-id="611" weight="2.270709215087931"/>
<connection id="674" src-id="62" dest-id="611" weight="-0.2709896474612363"/>
<connection id="675" src-id="63" dest-id="611" weight="-2.1480186684605647"/>
<connection id="676" src-id="64" dest-id="611" weight="-0.814470538814642"/>
<connection id="677" src-id="65" dest-id="611" weight="1.003932659966964"/>
<connection id="678" src-id="66" dest-id="611" weight="1.315196518805203"/>
<connection id="679" src-id="67" dest-id="611" weight="1.8629238428374917"/>
<connection id="680" src-id="68" dest-id="611" weight="3.6341538790676986"/>
<connection id="681" src-id="69" dest-id="611" weight="3.7214655152663267"/>
<connection id="682" src-id="70" dest-id="611" weight="0.1417890004902589"/>
<connection id="683" src-id="71" dest-id="611" weight="0.5230322145515575"/>
<connection id="684" src-id="72" dest-id="611" weight="-2.735282013817895"/>
<connection id="685" src-id="73" dest-id="611" weight="0.4253877778430284"/>
<connection id="686" src-id="74" dest-id="611" weight="-1.4008794008982395"/>
<connection id="687" src-id="75" dest-id="611" weight="-3.7197421345424613"/>
<connection id="688" src-id="76" dest-id="611" weight="-0.31240619264569847"/>
<connection id="689" src-id="77" dest-id="611" weight="0.39546855230680356"/>
<connection id="690" src-id="78" dest-id="611" weight="-1.4596513064118974"/>
<connection id="691" src-id="79" dest-id="611" weight="0.505965866726138"/>
<connection id="692" src-id="80" dest-id="611" weight="2.2535892397527517"/>
<connection id="693" src-id="81" dest-id="611" weight="0.20245405941775627"/>
<connection id="694" src-id="82" dest-id="611" weight="-0.18680729168333388"/>
<connection id="695" src-id="83" dest-id="611" weight="0.4625128288960184"/>
<connection id="696" src-id="84" dest-id="611" weight="3.3971270637078588"/>
<connection id="697" src-id="85" dest-id="611" weight="3.2215205231762556"/>
<connection id="698" src-id="86" dest-id="611" weight="2.3118378365032686"/>
<connection id="699" src-id="87" dest-id="611" weight="-1.7459184940745212"/>
<connection id="700" src-id="88" dest-id="611" weight="-0.29929622328588623"/>
<connection id="701" src-id="89" dest-id="611" weight="1.714460835099463"/>
<connection id="702" src-id="90" dest-id="611" weight="1.8124064997184834"/>
<connection id="703" src-id="91" dest-id="611" weight="-1.6295930429487058"/>
<connection id="704" src-id="92" dest-id="611" weight="1.7225175466803657"/>
<connection id="705" src-id="93" dest-id="611" weight="2.1068124308263734"/>
<connection id="706" src-id="94" dest-id="611" weight="-3.814916557008314"/>
<connection id="707" src-id="95" dest-id="611" weight="-0.40799759662039803"/>
<connection id="708" src-id="96" dest-id="611" weight="0.7283818836617123"/>
<connection id="709" src-id="97" dest-id="611" weight="-0.7052606344223022"/>
<connection id="710" src-id="98" dest-id="611" weight="0.6854589421325968"/>
<connection id="711" src-id="99" dest-id="611" weight="-0.14773307991591822"/>
<connection id="712" src-id="100" dest-id="611" weight="-0.477113558325136"/>
<neuron id="6846" type="hid" activation="sigmoid"/>
<connection id="6847" src-id="96" dest-id="6846" weight="1.0"/>
<connection id="6848" src-id="6846" dest-id="305" weight="2.0449473395139677"/>
<neuron id="7149" type="hid" activation="sigmoid"/>
<connection id="7150" src-id="27" dest-id="7149" weight="1.0"/>
<connection id="7151" src-id="7149" dest-id="203" weight="1.0009158708431047"/>
<neuron id="10311" type="hid" activation="sigmoid"/>
<connection id="10312" src-id="99" dest-id="10311" weight="0.5904757325520535"/>
<connection id="10313" src-id="10311" dest-id="203" weight="0.7663488494478945"/>
<neuron id="10413" type="hid" activation="sigmoid"/>
<connection id="10414" src-id="99" dest-id="10413" weight="-0.5562962158462135"/>
<connection id="10415" src-id="10413" dest-id="509" weight="2.4939715179904134"/>
<neuron id="10416" type="hid" activation="sigmoid"/>
<connection id="10417" src-id="73" dest-id="10416" weight="2.9030587807528168"/>
<connection id="10418" src-id="10416" dest-id="407" weight="1.4661954121564433"/>
<neuron id="10419" type="hid" activation="sigmoid"/>
<connection id="10420" src-id="50" dest-id="10419" weight="1.0"/>
<connection id="10421" src-id="10419" dest-id="509" weight="-2.917578174469785"/>
<connection id="14439" src-id="91" dest-id="10419" weight="0.1428773376112047"/>
</chromosome>