<chromosome id="21631"><neuron id="20911" type="in" activation="linear"/>
<neuron id="20912" type="in" activation="linear"/>
<neuron id="20913" type="in" activation="linear"/>
<neuron id="20914" type="in" activation="linear"/>
<neuron id="20915" type="in" activation="linear"/>
<neuron id="20916" type="in" activation="linear"/>
<neuron id="20917" type="in" activation="linear"/>
<neuron id="20918" type="in" activation="linear"/>
<neuron id="20919" type="in" activation="linear"/>
<neuron id="20920" type="in" activation="linear"/>
<neuron id="20921" type="in" activation="linear"/>
<neuron id="20922" type="in" activation="linear"/>
<neuron id="20923" type="in" activation="linear"/>
<neuron id="20924" type="in" activation="linear"/>
<neuron id="20925" type="in" activation="linear"/>
<neuron id="20926" type="in" activation="linear"/>
<neuron id="20927" type="in" activation="linear"/>
<neuron id="20928" type="in" activation="linear"/>
<neuron id="20929" type="in" activation="linear"/>
<neuron id="20930" type="in" activation="linear"/>
<neuron id="20931" type="in" activation="linear"/>
<neuron id="20932" type="in" activation="linear"/>
<neuron id="20933" type="in" activation="linear"/>
<neuron id="20934" type="in" activation="linear"/>
<neuron id="20935" type="in" activation="linear"/>
<neuron id="20936" type="in" activation="linear"/>
<neuron id="20937" type="in" activation="linear"/>
<neuron id="20938" type="in" activation="linear"/>
<neuron id="20939" type="in" activation="linear"/>
<neuron id="20940" type="in" activation="linear"/>
<neuron id="20941" type="in" activation="linear"/>
<neuron id="20942" type="in" activation="linear"/>
<neuron id="20943" type="in" activation="linear"/>
<neuron id="20944" type="in" activation="linear"/>
<neuron id="20945" type="in" activation="linear"/>
<neuron id="20946" type="in" activation="linear"/>
<neuron id="20947" type="in" activation="linear"/>
<neuron id="20948" type="in" activation="linear"/>
<neuron id="20949" type="in" activation="linear"/>
<neuron id="20950" type="in" activation="linear"/>
<neuron id="20951" type="in" activation="linear"/>
<neuron id="20952" type="in" activation="linear"/>
<neuron id="20953" type="in" activation="linear"/>
<neuron id="20954" type="in" activation="linear"/>
<neuron id="20955" type="in" activation="linear"/>
<neuron id="20956" type="in" activation="linear"/>
<neuron id="20957" type="in" activation="linear"/>
<neuron id="20958" type="in" activation="linear"/>
<neuron id="20959" type="in" activation="linear"/>
<neuron id="20960" type="in" activation="linear"/>
<neuron id="20961" type="in" activation="linear"/>
<neuron id="20962" type="in" activation="linear"/>
<neuron id="20963" type="in" activation="linear"/>
<neuron id="20964" type="in" activation="linear"/>
<neuron id="20965" type="in" activation="linear"/>
<neuron id="20966" type="in" activation="linear"/>
<neuron id="20967" type="in" activation="linear"/>
<neuron id="20968" type="in" activation="linear"/>
<neuron id="20969" type="in" activation="linear"/>
<neuron id="20970" type="in" activation="linear"/>
<neuron id="20971" type="in" activation="linear"/>
<neuron id="20972" type="in" activation="linear"/>
<neuron id="20973" type="in" activation="linear"/>
<neuron id="20974" type="in" activation="linear"/>
<neuron id="20975" type="in" activation="linear"/>
<neuron id="20976" type="in" activation="linear"/>
<neuron id="20977" type="in" activation="linear"/>
<neuron id="20978" type="in" activation="linear"/>
<neuron id="20979" type="in" activation="linear"/>
<neuron id="20980" type="in" activation="linear"/>
<neuron id="20981" type="in" activation="linear"/>
<neuron id="20982" type="in" activation="linear"/>
<neuron id="20983" type="in" activation="linear"/>
<neuron id="20984" type="in" activation="linear"/>
<neuron id="20985" type="in" activation="linear"/>
<neuron id="20986" type="in" activation="linear"/>
<neuron id="20987" type="in" activation="linear"/>
<neuron id="20988" type="in" activation="linear"/>
<neuron id="20989" type="in" activation="linear"/>
<neuron id="20990" type="in" activation="linear"/>
<neuron id="20991" type="in" activation="linear"/>
<neuron id="20992" type="in" activation="linear"/>
<neuron id="20993" type="in" activation="linear"/>
<neuron id="20994" type="in" activation="linear"/>
<neuron id="20995" type="in" activation="linear"/>
<neuron id="20996" type="in" activation="linear"/>
<neuron id="20997" type="in" activation="linear"/>
<neuron id="20998" type="in" activation="linear"/>
<neuron id="20999" type="in" activation="linear"/>
<neuron id="21000" type="in" activation="linear"/>
<neuron id="21001" type="in" activation="linear"/>
<neuron id="21002" type="in" activation="linear"/>
<neuron id="21003" type="in" activation="linear"/>
<neuron id="21004" type="in" activation="linear"/>
<neuron id="21005" type="in" activation="linear"/>
<neuron id="21006" type="in" activation="linear"/>
<neuron id="21007" type="in" activation="linear"/>
<neuron id="21008" type="in" activation="linear"/>
<neuron id="21009" type="in" activation="linear"/>
<neuron id="21010" type="in" activation="linear"/>
<neuron id="21011" type="in" activation="linear"/>
<neuron id="21012" type="out" activation="sigmoid"/>
<connection id="21013" src-id="20911" dest-id="21012" weight="0.7977273464202881"/>
<connection id="21014" src-id="20912" dest-id="21012" weight="0.5309375524520874"/>
<connection id="21015" src-id="20913" dest-id="21012" weight="0.4077380895614624"/>
<connection id="21016" src-id="20914" dest-id="21012" weight="0.9939873218536377"/>
<connection id="21017" src-id="20915" dest-id="21012" weight="-0.9856011867523193"/>
<connection id="21018" src-id="20916" dest-id="21012" weight="0.42615020275115967"/>
<connection id="21019" src-id="20917" dest-id="21012" weight="-0.5702530145645142"/>
<connection id="21020" src-id="20918" dest-id="21012" weight="0.8075416088104248"/>
<connection id="21021" src-id="20919" dest-id="21012" weight="-0.9592807292938232"/>
<connection id="21022" src-id="20920" dest-id="21012" weight="-0.9364926815032959"/>
<connection id="21023" src-id="20921" dest-id="21012" weight="-0.9685090780258179"/>
<connection id="21024" src-id="20922" dest-id="21012" weight="-0.5847376585006714"/>
<connection id="21025" src-id="20923" dest-id="21012" weight="-0.9806957244873047"/>
<connection id="21026" src-id="20924" dest-id="21012" weight="0.7015030384063721"/>
<connection id="21027" src-id="20925" dest-id="21012" weight="0.8755671977996826"/>
<connection id="21028" src-id="20926" dest-id="21012" weight="-0.2900141477584839"/>
<connection id="21029" src-id="20927" dest-id="21012" weight="-0.291843056678772"/>
<connection id="21030" src-id="20928" dest-id="21012" weight="-0.9771231412887573"/>
<connection id="21031" src-id="20929" dest-id="21012" weight="0.743344783782959"/>
<connection id="21032" src-id="20930" dest-id="21012" weight="0.5372135639190674"/>
<connection id="21033" src-id="20931" dest-id="21012" weight="-0.9682159423828125"/>
<connection id="21034" src-id="20932" dest-id="21012" weight="0.5951422452926636"/>
<connection id="21035" src-id="20933" dest-id="21012" weight="0.36728978157043457"/>
<connection id="21036" src-id="20934" dest-id="21012" weight="-0.49882686138153076"/>
<connection id="21037" src-id="20935" dest-id="21012" weight="-0.6949292421340942"/>
<connection id="21038" src-id="20936" dest-id="21012" weight="-0.8863053321838379"/>
<connection id="21039" src-id="20937" dest-id="21012" weight="0.8480379581451416"/>
<connection id="21040" src-id="20938" dest-id="21012" weight="0.2803945541381836"/>
<connection id="21041" src-id="20939" dest-id="21012" weight="-0.008756399154663086"/>
<connection id="21042" src-id="20940" dest-id="21012" weight="-0.059583425521850586"/>
<connection id="21043" src-id="20941" dest-id="21012" weight="0.10710108280181885"/>
<connection id="21044" src-id="20942" dest-id="21012" weight="-0.6181983947753906"/>
<connection id="21045" src-id="20943" dest-id="21012" weight="0.615944504737854"/>
<connection id="21046" src-id="20944" dest-id="21012" weight="-0.2787550687789917"/>
<connection id="21047" src-id="20945" dest-id="21012" weight="-0.9382960796356201"/>
<connection id="21048" src-id="20946" dest-id="21012" weight="-0.732701301574707"/>
<connection id="21049" src-id="20947" dest-id="21012" weight="0.34231746196746826"/>
<connection id="21050" src-id="20948" dest-id="21012" weight="-0.856817364692688"/>
<connection id="21051" src-id="20949" dest-id="21012" weight="-0.9134540557861328"/>
<connection id="21052" src-id="20950" dest-id="21012" weight="0.03363907337188721"/>
<connection id="21053" src-id="20951" dest-id="21012" weight="0.39091193675994873"/>
<connection id="21054" src-id="20952" dest-id="21012" weight="-0.3780163526535034"/>
<connection id="21055" src-id="20953" dest-id="21012" weight="-0.3997572660446167"/>
<connection id="21056" src-id="20954" dest-id="21012" weight="-0.7221271991729736"/>
<connection id="21057" src-id="20955" dest-id="21012" weight="0.9182089567184448"/>
<connection id="21058" src-id="20956" dest-id="21012" weight="0.999746561050415"/>
<connection id="21059" src-id="20957" dest-id="21012" weight="-0.434985876083374"/>
<connection id="21060" src-id="20958" dest-id="21012" weight="-0.6939558982849121"/>
<connection id="21061" src-id="20959" dest-id="21012" weight="-0.11500263214111328"/>
<connection id="21062" src-id="20960" dest-id="21012" weight="0.43666958808898926"/>
<connection id="21063" src-id="20961" dest-id="21012" weight="0.6313097476959229"/>
<connection id="21064" src-id="20962" dest-id="21012" weight="-0.28258538246154785"/>
<connection id="21065" src-id="20963" dest-id="21012" weight="-0.13173091411590576"/>
<connection id="21066" src-id="20964" dest-id="21012" weight="-0.48073136806488037"/>
<connection id="21067" src-id="20965" dest-id="21012" weight="-0.5598049163818359"/>
<connection id="21068" src-id="20966" dest-id="21012" weight="0.8019870519638062"/>
<connection id="21069" src-id="20967" dest-id="21012" weight="-0.5034438371658325"/>
<connection id="21070" src-id="20968" dest-id="21012" weight="0.25071048736572266"/>
<connection id="21071" src-id="20969" dest-id="21012" weight="0.09242761135101318"/>
<connection id="21072" src-id="20970" dest-id="21012" weight="0.7133712768554688"/>
<connection id="21073" src-id="20971" dest-id="21012" weight="-0.7011820077896118"/>
<connection id="21074" src-id="20972" dest-id="21012" weight="0.7660766839981079"/>
<connection id="21075" src-id="20973" dest-id="21012" weight="0.41241931915283203"/>
<connection id="21076" src-id="20974" dest-id="21012" weight="-0.4837808609008789"/>
<connection id="21077" src-id="20975" dest-id="21012" weight="0.1123967170715332"/>
<connection id="21078" src-id="20976" dest-id="21012" weight="-0.7888892889022827"/>
<connection id="21079" src-id="20977" dest-id="21012" weight="0.8171737194061279"/>
<connection id="21080" src-id="20978" dest-id="21012" weight="-0.14205539226531982"/>
<connection id="21081" src-id="20979" dest-id="21012" weight="-0.06120634078979492"/>
<connection id="21082" src-id="20980" dest-id="21012" weight="-0.22165727615356445"/>
<connection id="21083" src-id="20981" dest-id="21012" weight="0.3155066967010498"/>
<connection id="21084" src-id="20982" dest-id="21012" weight="0.9848809242248535"/>
<connection id="21085" src-id="20983" dest-id="21012" weight="0.19089674949645996"/>
<connection id="21086" src-id="20984" dest-id="21012" weight="-0.8933241367340088"/>
<connection id="21087" src-id="20985" dest-id="21012" weight="-0.5866466760635376"/>
<connection id="21088" src-id="20986" dest-id="21012" weight="0.32630133628845215"/>
<connection id="21089" src-id="20987" dest-id="21012" weight="0.8468930721282959"/>
<connection id="21090" src-id="20988" dest-id="21012" weight="-0.5269019603729248"/>
<connection id="21091" src-id="20989" dest-id="21012" weight="-0.980059027671814"/>
<connection id="21092" src-id="20990" dest-id="21012" weight="0.024978280067443848"/>
<connection id="21093" src-id="20991" dest-id="21012" weight="-0.8992491960525513"/>
<connection id="21094" src-id="20992" dest-id="21012" weight="-0.05211019515991211"/>
<connection id="21095" src-id="20993" dest-id="21012" weight="0.40152084827423096"/>
<connection id="21096" src-id="20994" dest-id="21012" weight="-0.8744239807128906"/>
<connection id="21097" src-id="20995" dest-id="21012" weight="-0.0555574893951416"/>
<connection id="21098" src-id="20996" dest-id="21012" weight="0.11357462406158447"/>
<connection id="21099" src-id="20997" dest-id="21012" weight="0.9099011421203613"/>
<connection id="21100" src-id="20998" dest-id="21012" weight="0.0737990140914917"/>
<connection id="21101" src-id="20999" dest-id="21012" weight="-0.21818184852600098"/>
<connection id="21102" src-id="21000" dest-id="21012" weight="-0.6148492097854614"/>
<connection id="21103" src-id="21001" dest-id="21012" weight="-0.25083720684051514"/>
<connection id="21104" src-id="21002" dest-id="21012" weight="-0.4322551488876343"/>
<connection id="21105" src-id="21003" dest-id="21012" weight="-0.011680364608764648"/>
<connection id="21106" src-id="21004" dest-id="21012" weight="-0.606623649597168"/>
<connection id="21107" src-id="21005" dest-id="21012" weight="-0.9061249494552612"/>
<connection id="21108" src-id="21006" dest-id="21012" weight="0.3824784755706787"/>
<connection id="21109" src-id="21007" dest-id="21012" weight="-0.5941345691680908"/>
<connection id="21110" src-id="21008" dest-id="21012" weight="-0.5611857175827026"/>
<connection id="21111" src-id="21009" dest-id="21012" weight="0.12531089782714844"/>
<connection id="21112" src-id="21010" dest-id="21012" weight="-0.29016005992889404"/>
<connection id="21113" src-id="21011" dest-id="21012" weight="-0.5091782808303833"/>
<neuron id="21114" type="out" activation="sigmoid"/>
<connection id="21115" src-id="20911" dest-id="21114" weight="-0.5169967412948608"/>
<connection id="21116" src-id="20912" dest-id="21114" weight="-0.7707116603851318"/>
<connection id="21117" src-id="20913" dest-id="21114" weight="-0.12543010711669922"/>
<connection id="21118" src-id="20914" dest-id="21114" weight="-0.6111713647842407"/>
<connection id="21119" src-id="20915" dest-id="21114" weight="-0.5382404327392578"/>
<connection id="21120" src-id="20916" dest-id="21114" weight="-0.04769241809844971"/>
<connection id="21121" src-id="20917" dest-id="21114" weight="0.4678645133972168"/>
<connection id="21122" src-id="20918" dest-id="21114" weight="-0.9515435695648193"/>
<connection id="21123" src-id="20919" dest-id="21114" weight="0.48775970935821533"/>
<connection id="21124" src-id="20920" dest-id="21114" weight="0.12478506565093994"/>
<connection id="21125" src-id="20921" dest-id="21114" weight="-0.6503912210464478"/>
<connection id="21126" src-id="20922" dest-id="21114" weight="-0.1574559211730957"/>
<connection id="21127" src-id="20923" dest-id="21114" weight="0.514959454536438"/>
<connection id="21128" src-id="20924" dest-id="21114" weight="-0.3541034460067749"/>
<connection id="21129" src-id="20925" dest-id="21114" weight="-0.6138417720794678"/>
<connection id="21130" src-id="20926" dest-id="21114" weight="0.5592082738876343"/>
<connection id="21131" src-id="20927" dest-id="21114" weight="-0.3178977966308594"/>
<connection id="21132" src-id="20928" dest-id="21114" weight="0.12949681282043457"/>
<connection id="21133" src-id="20929" dest-id="21114" weight="-0.10669314861297607"/>
<connection id="21134" src-id="20930" dest-id="21114" weight="0.35273098945617676"/>
<connection id="21135" src-id="20931" dest-id="21114" weight="0.40880119800567627"/>
<connection id="21136" src-id="20932" dest-id="21114" weight="-0.6882325410842896"/>
<connection id="21137" src-id="20933" dest-id="21114" weight="0.631854772567749"/>
<connection id="21138" src-id="20934" dest-id="21114" weight="-0.11208927631378174"/>
<connection id="21139" src-id="20935" dest-id="21114" weight="0.6139911413192749"/>
<connection id="21140" src-id="20936" dest-id="21114" weight="0.7268431186676025"/>
<connection id="21141" src-id="20937" dest-id="21114" weight="0.8501485586166382"/>
<connection id="21142" src-id="20938" dest-id="21114" weight="0.8313306570053101"/>
<connection id="21143" src-id="20939" dest-id="21114" weight="0.547669529914856"/>
<connection id="21144" src-id="20940" dest-id="21114" weight="0.6061333417892456"/>
<connection id="21145" src-id="20941" dest-id="21114" weight="0.6844632625579834"/>
<connection id="21146" src-id="20942" dest-id="21114" weight="0.6819361448287964"/>
<connection id="21147" src-id="20943" dest-id="21114" weight="-0.28617024421691895"/>
<connection id="21148" src-id="20944" dest-id="21114" weight="-0.27889323234558105"/>
<connection id="21149" src-id="20945" dest-id="21114" weight="-0.479195237159729"/>
<connection id="21150" src-id="20946" dest-id="21114" weight="-0.8848593235015869"/>
<connection id="21151" src-id="20947" dest-id="21114" weight="-0.5874289274215698"/>
<connection id="21152" src-id="20948" dest-id="21114" weight="-0.530123233795166"/>
<connection id="21153" src-id="20949" dest-id="21114" weight="0.4034949541091919"/>
<connection id="21154" src-id="20950" dest-id="21114" weight="0.24448847770690918"/>
<connection id="21155" src-id="20951" dest-id="21114" weight="0.3960881233215332"/>
<connection id="21156" src-id="20952" dest-id="21114" weight="-0.06176769733428955"/>
<connection id="21157" src-id="20953" dest-id="21114" weight="0.8659189939498901"/>
<connection id="21158" src-id="20954" dest-id="21114" weight="-0.030993342399597168"/>
<connection id="21159" src-id="20955" dest-id="21114" weight="-0.973658561706543"/>
<connection id="21160" src-id="20956" dest-id="21114" weight="0.010250091552734375"/>
<connection id="21161" src-id="20957" dest-id="21114" weight="-0.31754958629608154"/>
<connection id="21162" src-id="20958" dest-id="21114" weight="-0.35963404178619385"/>
<connection id="21163" src-id="20959" dest-id="21114" weight="-0.19227266311645508"/>
<connection id="21164" src-id="20960" dest-id="21114" weight="-0.5420011281967163"/>
<connection id="21165" src-id="20961" dest-id="21114" weight="0.9294614791870117"/>
<connection id="21166" src-id="20962" dest-id="21114" weight="-0.7993347644805908"/>
<connection id="21167" src-id="20963" dest-id="21114" weight="0.06824707984924316"/>
<connection id="21168" src-id="20964" dest-id="21114" weight="0.9310693740844727"/>
<connection id="21169" src-id="20965" dest-id="21114" weight="0.7353675365447998"/>
<connection id="21170" src-id="20966" dest-id="21114" weight="-0.4608635902404785"/>
<connection id="21171" src-id="20967" dest-id="21114" weight="-0.6439496278762817"/>
<connection id="21172" src-id="20968" dest-id="21114" weight="0.05292034149169922"/>
<connection id="21173" src-id="20969" dest-id="21114" weight="0.43898916244506836"/>
<connection id="21174" src-id="20970" dest-id="21114" weight="0.7056567668914795"/>
<connection id="21175" src-id="20971" dest-id="21114" weight="0.4395531415939331"/>
<connection id="21176" src-id="20972" dest-id="21114" weight="0.6017968654632568"/>
<connection id="21177" src-id="20973" dest-id="21114" weight="0.21252787113189697"/>
<connection id="21178" src-id="20974" dest-id="21114" weight="0.6932497024536133"/>
<connection id="21179" src-id="20975" dest-id="21114" weight="0.9396282434463501"/>
<connection id="21180" src-id="20976" dest-id="21114" weight="-0.2700687646865845"/>
<connection id="21181" src-id="20977" dest-id="21114" weight="-0.9032144546508789"/>
<connection id="21182" src-id="20978" dest-id="21114" weight="-0.5654417276382446"/>
<connection id="21183" src-id="20979" dest-id="21114" weight="-0.9710991382598877"/>
<connection id="21184" src-id="20980" dest-id="21114" weight="-0.8921443223953247"/>
<connection id="21185" src-id="20981" dest-id="21114" weight="0.8048039674758911"/>
<connection id="21186" src-id="20982" dest-id="21114" weight="-0.5963165760040283"/>
<connection id="21187" src-id="20983" dest-id="21114" weight="0.40945935249328613"/>
<connection id="21188" src-id="20984" dest-id="21114" weight="-0.9458823204040527"/>
<connection id="21189" src-id="20985" dest-id="21114" weight="0.44500160217285156"/>
<connection id="21190" src-id="20986" dest-id="21114" weight="-0.48888731002807617"/>
<connection id="21191" src-id="20987" dest-id="21114" weight="-0.8139013051986694"/>
<connection id="21192" src-id="20988" dest-id="21114" weight="-0.5610212087631226"/>
<connection id="21193" src-id="20989" dest-id="21114" weight="-0.22847580909729004"/>
<connection id="21194" src-id="20990" dest-id="21114" weight="-0.15669596195220947"/>
<connection id="21195" src-id="20991" dest-id="21114" weight="0.20353913307189941"/>
<connection id="21196" src-id="20992" dest-id="21114" weight="-0.7205429077148438"/>
<connection id="21197" src-id="20993" dest-id="21114" weight="-0.13044631481170654"/>
<connection id="21198" src-id="20994" dest-id="21114" weight="0.028658151626586914"/>
<connection id="21199" src-id="20995" dest-id="21114" weight="0.9851982593536377"/>
<connection id="21200" src-id="20996" dest-id="21114" weight="-0.6506574153900146"/>
<connection id="21201" src-id="20997" dest-id="21114" weight="0.9146206378936768"/>
<connection id="21202" src-id="20998" dest-id="21114" weight="0.6881973743438721"/>
<connection id="21203" src-id="20999" dest-id="21114" weight="0.3265327215194702"/>
<connection id="21204" src-id="21000" dest-id="21114" weight="-0.7802668809890747"/>
<connection id="21205" src-id="21001" dest-id="21114" weight="0.3016778230667114"/>
<connection id="21206" src-id="21002" dest-id="21114" weight="-0.5864087343215942"/>
<connection id="21207" src-id="21003" dest-id="21114" weight="-0.2575056552886963"/>
<connection id="21208" src-id="21004" dest-id="21114" weight="0.3626912832260132"/>
<connection id="21209" src-id="21005" dest-id="21114" weight="-0.07778239250183105"/>
<connection id="21210" src-id="21006" dest-id="21114" weight="-0.8501964807510376"/>
<connection id="21211" src-id="21007" dest-id="21114" weight="0.8872566223144531"/>
<connection id="21212" src-id="21008" dest-id="21114" weight="-0.736504316329956"/>
<connection id="21213" src-id="21009" dest-id="21114" weight="-0.5173193216323853"/>
<connection id="21214" src-id="21010" dest-id="21114" weight="0.6684261560440063"/>
<connection id="21215" src-id="21011" dest-id="21114" weight="0.4523499011993408"/>
<neuron id="21216" type="out" activation="sigmoid"/>
<connection id="21217" src-id="20911" dest-id="21216" weight="0.8976113796234131"/>
<connection id="21218" src-id="20912" dest-id="21216" weight="0.7177071571350098"/>
<connection id="21219" src-id="20913" dest-id="21216" weight="-0.7942310571670532"/>
<connection id="21220" src-id="20914" dest-id="21216" weight="0.26019418239593506"/>
<connection id="21221" src-id="20915" dest-id="21216" weight="0.9701385498046875"/>
<connection id="21222" src-id="20916" dest-id="21216" weight="-0.723433256149292"/>
<connection id="21223" src-id="20917" dest-id="21216" weight="0.2933356761932373"/>
<connection id="21224" src-id="20918" dest-id="21216" weight="-0.186484694480896"/>
<connection id="21225" src-id="20919" dest-id="21216" weight="0.5525672435760498"/>
<connection id="21226" src-id="20920" dest-id="21216" weight="0.4757496118545532"/>
<connection id="21227" src-id="20921" dest-id="21216" weight="0.5950068235397339"/>
<connection id="21228" src-id="20922" dest-id="21216" weight="0.6032819747924805"/>
<connection id="21229" src-id="20923" dest-id="21216" weight="-0.7201300859451294"/>
<connection id="21230" src-id="20924" dest-id="21216" weight="-0.5531374216079712"/>
<connection id="21231" src-id="20925" dest-id="21216" weight="-0.766103982925415"/>
<connection id="21232" src-id="20926" dest-id="21216" weight="-0.6591238975524902"/>
<connection id="21233" src-id="20927" dest-id="21216" weight="0.21726298332214355"/>
<connection id="21234" src-id="20928" dest-id="21216" weight="-0.6954703330993652"/>
<connection id="21235" src-id="20929" dest-id="21216" weight="0.9725335836410522"/>
<connection id="21236" src-id="20930" dest-id="21216" weight="0.9427233934402466"/>
<connection id="21237" src-id="20931" dest-id="21216" weight="-0.47144365310668945"/>
<connection id="21238" src-id="20932" dest-id="21216" weight="-0.441900372505188"/>
<connection id="21239" src-id="20933" dest-id="21216" weight="0.8140755891799927"/>
<connection id="21240" src-id="20934" dest-id="21216" weight="0.6923284530639648"/>
<connection id="21241" src-id="20935" dest-id="21216" weight="-0.133650541305542"/>
<connection id="21242" src-id="20936" dest-id="21216" weight="-0.7560161352157593"/>
<connection id="21243" src-id="20937" dest-id="21216" weight="-0.487770676612854"/>
<connection id="21244" src-id="20938" dest-id="21216" weight="-0.673403263092041"/>
<connection id="21245" src-id="20939" dest-id="21216" weight="-0.8208792209625244"/>
<connection id="21246" src-id="20940" dest-id="21216" weight="-0.7809422016143799"/>
<connection id="21247" src-id="20941" dest-id="21216" weight="0.28734660148620605"/>
<connection id="21248" src-id="20942" dest-id="21216" weight="-0.21225249767303467"/>
<connection id="21249" src-id="20943" dest-id="21216" weight="0.6434458494186401"/>
<connection id="21250" src-id="20944" dest-id="21216" weight="0.19261229038238525"/>
<connection id="21251" src-id="20945" dest-id="21216" weight="0.20074677467346191"/>
<connection id="21252" src-id="20946" dest-id="21216" weight="-0.34745287895202637"/>
<connection id="21253" src-id="20947" dest-id="21216" weight="0.4643806219100952"/>
<connection id="21254" src-id="20948" dest-id="21216" weight="0.7540123462677002"/>
<connection id="21255" src-id="20949" dest-id="21216" weight="-0.6248840093612671"/>
<connection id="21256" src-id="20950" dest-id="21216" weight="-0.4432187080383301"/>
<connection id="21257" src-id="20951" dest-id="21216" weight="0.15790164470672607"/>
<connection id="21258" src-id="20952" dest-id="21216" weight="-0.34912562370300293"/>
<connection id="21259" src-id="20953" dest-id="21216" weight="-0.9166274070739746"/>
<connection id="21260" src-id="20954" dest-id="21216" weight="-0.3091402053833008"/>
<connection id="21261" src-id="20955" dest-id="21216" weight="0.9819140434265137"/>
<connection id="21262" src-id="20956" dest-id="21216" weight="-0.43013274669647217"/>
<connection id="21263" src-id="20957" dest-id="21216" weight="0.9605104923248291"/>
<connection id="21264" src-id="20958" dest-id="21216" weight="0.22446370124816895"/>
<connection id="21265" src-id="20959" dest-id="21216" weight="-0.2063232660293579"/>
<connection id="21266" src-id="20960" dest-id="21216" weight="0.7570576667785645"/>
<connection id="21267" src-id="20961" dest-id="21216" weight="-0.19727826118469238"/>
<connection id="21268" src-id="20962" dest-id="21216" weight="0.5527342557907104"/>
<connection id="21269" src-id="20963" dest-id="21216" weight="0.6897461414337158"/>
<connection id="21270" src-id="20964" dest-id="21216" weight="-0.018800973892211914"/>
<connection id="21271" src-id="20965" dest-id="21216" weight="-0.03313100337982178"/>
<connection id="21272" src-id="20966" dest-id="21216" weight="0.9284117221832275"/>
<connection id="21273" src-id="20967" dest-id="21216" weight="0.2691681385040283"/>
<connection id="21274" src-id="20968" dest-id="21216" weight="0.9919052124023438"/>
<connection id="21275" src-id="20969" dest-id="21216" weight="-0.08627510070800781"/>
<connection id="21276" src-id="20970" dest-id="21216" weight="0.3945910930633545"/>
<connection id="21277" src-id="20971" dest-id="21216" weight="-0.2776505947113037"/>
<connection id="21278" src-id="20972" dest-id="21216" weight="0.06187617778778076"/>
<connection id="21279" src-id="20973" dest-id="21216" weight="0.37413203716278076"/>
<connection id="21280" src-id="20974" dest-id="21216" weight="-0.8413668870925903"/>
<connection id="21281" src-id="20975" dest-id="21216" weight="0.6887693405151367"/>
<connection id="21282" src-id="20976" dest-id="21216" weight="0.14117026329040527"/>
<connection id="21283" src-id="20977" dest-id="21216" weight="0.6634458303451538"/>
<connection id="21284" src-id="20978" dest-id="21216" weight="0.5027580261230469"/>
<connection id="21285" src-id="20979" dest-id="21216" weight="-0.020343661308288574"/>
<connection id="21286" src-id="20980" dest-id="21216" weight="0.2110581398010254"/>
<connection id="21287" src-id="20981" dest-id="21216" weight="-0.6873595714569092"/>
<connection id="21288" src-id="20982" dest-id="21216" weight="-0.9792612791061401"/>
<connection id="21289" src-id="20983" dest-id="21216" weight="0.8913975954055786"/>
<connection id="21290" src-id="20984" dest-id="21216" weight="0.6306637525558472"/>
<connection id="21291" src-id="20985" dest-id="21216" weight="-0.8081547021865845"/>
<connection id="21292" src-id="20986" dest-id="21216" weight="0.06890261173248291"/>
<connection id="21293" src-id="20987" dest-id="21216" weight="0.5374855995178223"/>
<connection id="21294" src-id="20988" dest-id="21216" weight="0.5530208349227905"/>
<connection id="21295" src-id="20989" dest-id="21216" weight="-0.7773141860961914"/>
<connection id="21296" src-id="20990" dest-id="21216" weight="-0.3543827533721924"/>
<connection id="21297" src-id="20991" dest-id="21216" weight="-0.9718197584152222"/>
<connection id="21298" src-id="20992" dest-id="21216" weight="0.18624603748321533"/>
<connection id="21299" src-id="20993" dest-id="21216" weight="0.4396846294403076"/>
<connection id="21300" src-id="20994" dest-id="21216" weight="0.9450865983963013"/>
<connection id="21301" src-id="20995" dest-id="21216" weight="0.5859841108322144"/>
<connection id="21302" src-id="20996" dest-id="21216" weight="0.03439474105834961"/>
<connection id="21303" src-id="20997" dest-id="21216" weight="0.17948400974273682"/>
<connection id="21304" src-id="20998" dest-id="21216" weight="-0.7966008186340332"/>
<connection id="21305" src-id="20999" dest-id="21216" weight="-0.009058475494384766"/>
<connection id="21306" src-id="21000" dest-id="21216" weight="-0.07838988304138184"/>
<connection id="21307" src-id="21001" dest-id="21216" weight="0.442341685295105"/>
<connection id="21308" src-id="21002" dest-id="21216" weight="-0.5416598320007324"/>
<connection id="21309" src-id="21003" dest-id="21216" weight="-0.1766057014465332"/>
<connection id="21310" src-id="21004" dest-id="21216" weight="-0.8609580993652344"/>
<connection id="21311" src-id="21005" dest-id="21216" weight="0.6570689678192139"/>
<connection id="21312" src-id="21006" dest-id="21216" weight="-0.07320106029510498"/>
<connection id="21313" src-id="21007" dest-id="21216" weight="-0.4349120855331421"/>
<connection id="21314" src-id="21008" dest-id="21216" weight="0.41958749294281006"/>
<connection id="21315" src-id="21009" dest-id="21216" weight="-0.8566116094589233"/>
<connection id="21316" src-id="21010" dest-id="21216" weight="0.9681657552719116"/>
<connection id="21317" src-id="21011" dest-id="21216" weight="-0.9843441247940063"/>
<neuron id="21318" type="out" activation="sigmoid"/>
<connection id="21319" src-id="20911" dest-id="21318" weight="0.5099408626556396"/>
<connection id="21320" src-id="20912" dest-id="21318" weight="0.24093472957611084"/>
<connection id="21321" src-id="20913" dest-id="21318" weight="-0.6913092136383057"/>
<connection id="21322" src-id="20914" dest-id="21318" weight="-0.005059957504272461"/>
<connection id="21323" src-id="20915" dest-id="21318" weight="0.14810550212860107"/>
<connection id="21324" src-id="20916" dest-id="21318" weight="-0.6206413507461548"/>
<connection id="21325" src-id="20917" dest-id="21318" weight="0.2663968801498413"/>
<connection id="21326" src-id="20918" dest-id="21318" weight="0.7780542373657227"/>
<connection id="21327" src-id="20919" dest-id="21318" weight="-0.5509130954742432"/>
<connection id="21328" src-id="20920" dest-id="21318" weight="0.09807956218719482"/>
<connection id="21329" src-id="20921" dest-id="21318" weight="0.21104145050048828"/>
<connection id="21330" src-id="20922" dest-id="21318" weight="-0.9734859466552734"/>
<connection id="21331" src-id="20923" dest-id="21318" weight="0.6398100852966309"/>
<connection id="21332" src-id="20924" dest-id="21318" weight="-0.7327868938446045"/>
<connection id="21333" src-id="20925" dest-id="21318" weight="-0.8526444435119629"/>
<connection id="21334" src-id="20926" dest-id="21318" weight="0.5433346033096313"/>
<connection id="21335" src-id="20927" dest-id="21318" weight="-0.7394436597824097"/>
<connection id="21336" src-id="20928" dest-id="21318" weight="0.3744354248046875"/>
<connection id="21337" src-id="20929" dest-id="21318" weight="0.007085323333740234"/>
<connection id="21338" src-id="20930" dest-id="21318" weight="0.43220818042755127"/>
<connection id="21339" src-id="20931" dest-id="21318" weight="-0.7352381944656372"/>
<connection id="21340" src-id="20932" dest-id="21318" weight="-0.13141536712646484"/>
<connection id="21341" src-id="20933" dest-id="21318" weight="-0.48273634910583496"/>
<connection id="21342" src-id="20934" dest-id="21318" weight="0.15139877796173096"/>
<connection id="21343" src-id="20935" dest-id="21318" weight="0.7085254192352295"/>
<connection id="21344" src-id="20936" dest-id="21318" weight="0.1134941577911377"/>
<connection id="21345" src-id="20937" dest-id="21318" weight="0.07589638233184814"/>
<connection id="21346" src-id="20938" dest-id="21318" weight="-0.47619736194610596"/>
<connection id="21347" src-id="20939" dest-id="21318" weight="-0.8614984750747681"/>
<connection id="21348" src-id="20940" dest-id="21318" weight="0.7099676132202148"/>
<connection id="21349" src-id="20941" dest-id="21318" weight="0.26538383960723877"/>
<connection id="21350" src-id="20942" dest-id="21318" weight="-0.4710897207260132"/>
<connection id="21351" src-id="20943" dest-id="21318" weight="0.48117291927337646"/>
<connection id="21352" src-id="20944" dest-id="21318" weight="0.7762681245803833"/>
<connection id="21353" src-id="20945" dest-id="21318" weight="-0.021726250648498535"/>
<connection id="21354" src-id="20946" dest-id="21318" weight="0.22463524341583252"/>
<connection id="21355" src-id="20947" dest-id="21318" weight="0.7331751585006714"/>
<connection id="21356" src-id="20948" dest-id="21318" weight="0.5055922269821167"/>
<connection id="21357" src-id="20949" dest-id="21318" weight="0.7853763103485107"/>
<connection id="21358" src-id="20950" dest-id="21318" weight="-0.4771702289581299"/>
<connection id="21359" src-id="20951" dest-id="21318" weight="0.48303794860839844"/>
<connection id="21360" src-id="20952" dest-id="21318" weight="0.9915553331375122"/>
<connection id="21361" src-id="20953" dest-id="21318" weight="-0.534873366355896"/>
<connection id="21362" src-id="20954" dest-id="21318" weight="0.8987674713134766"/>
<connection id="21363" src-id="20955" dest-id="21318" weight="-0.9027054309844971"/>
<connection id="21364" src-id="20956" dest-id="21318" weight="-0.7401994466781616"/>
<connection id="21365" src-id="20957" dest-id="21318" weight="-0.4861217737197876"/>
<connection id="21366" src-id="20958" dest-id="21318" weight="-0.889885663986206"/>
<connection id="21367" src-id="20959" dest-id="21318" weight="0.022544026374816895"/>
<connection id="21368" src-id="20960" dest-id="21318" weight="-0.22319841384887695"/>
<connection id="21369" src-id="20961" dest-id="21318" weight="0.10430657863616943"/>
<connection id="21370" src-id="20962" dest-id="21318" weight="0.32440876960754395"/>
<connection id="21371" src-id="20963" dest-id="21318" weight="0.24010539054870605"/>
<connection id="21372" src-id="20964" dest-id="21318" weight="0.8183248043060303"/>
<connection id="21373" src-id="20965" dest-id="21318" weight="0.14432334899902344"/>
<connection id="21374" src-id="20966" dest-id="21318" weight="0.926508903503418"/>
<connection id="21375" src-id="20967" dest-id="21318" weight="0.5180418491363525"/>
<connection id="21376" src-id="20968" dest-id="21318" weight="0.14368438720703125"/>
<connection id="21377" src-id="20969" dest-id="21318" weight="0.7591043710708618"/>
<connection id="21378" src-id="20970" dest-id="21318" weight="0.9508209228515625"/>
<connection id="21379" src-id="20971" dest-id="21318" weight="0.19941937923431396"/>
<connection id="21380" src-id="20972" dest-id="21318" weight="-0.10706126689910889"/>
<connection id="21381" src-id="20973" dest-id="21318" weight="-0.7224597930908203"/>
<connection id="21382" src-id="20974" dest-id="21318" weight="0.3405674695968628"/>
<connection id="21383" src-id="20975" dest-id="21318" weight="-0.7851370573043823"/>
<connection id="21384" src-id="20976" dest-id="21318" weight="0.7388707399368286"/>
<connection id="21385" src-id="20977" dest-id="21318" weight="-0.5886093378067017"/>
<connection id="21386" src-id="20978" dest-id="21318" weight="-0.10762369632720947"/>
<connection id="21387" src-id="20979" dest-id="21318" weight="0.5871647596359253"/>
<connection id="21388" src-id="20980" dest-id="21318" weight="0.6015399694442749"/>
<connection id="21389" src-id="20981" dest-id="21318" weight="-0.8133230209350586"/>
<connection id="21390" src-id="20982" dest-id="21318" weight="-0.8552590608596802"/>
<connection id="21391" src-id="20983" dest-id="21318" weight="0.5875173807144165"/>
<connection id="21392" src-id="20984" dest-id="21318" weight="-0.030771613121032715"/>
<connection id="21393" src-id="20985" dest-id="21318" weight="-0.10535192489624023"/>
<connection id="21394" src-id="20986" dest-id="21318" weight="0.9903973340988159"/>
<connection id="21395" src-id="20987" dest-id="21318" weight="0.9947936534881592"/>
<connection id="21396" src-id="20988" dest-id="21318" weight="0.6457899808883667"/>
<connection id="21397" src-id="20989" dest-id="21318" weight="0.1025233268737793"/>
<connection id="21398" src-id="20990" dest-id="21318" weight="-0.6564252376556396"/>
<connection id="21399" src-id="20991" dest-id="21318" weight="-0.4046891927719116"/>
<connection id="21400" src-id="20992" dest-id="21318" weight="0.9220969676971436"/>
<connection id="21401" src-id="20993" dest-id="21318" weight="-0.013093352317810059"/>
<connection id="21402" src-id="20994" dest-id="21318" weight="-0.2871420383453369"/>
<connection id="21403" src-id="20995" dest-id="21318" weight="-0.4589221477508545"/>
<connection id="21404" src-id="20996" dest-id="21318" weight="0.39102470874786377"/>
<connection id="21405" src-id="20997" dest-id="21318" weight="-0.03369128704071045"/>
<connection id="21406" src-id="20998" dest-id="21318" weight="-0.5102410316467285"/>
<connection id="21407" src-id="20999" dest-id="21318" weight="-0.23370599746704102"/>
<connection id="21408" src-id="21000" dest-id="21318" weight="0.31505775451660156"/>
<connection id="21409" src-id="21001" dest-id="21318" weight="-0.9891397953033447"/>
<connection id="21410" src-id="21002" dest-id="21318" weight="0.6639816761016846"/>
<connection id="21411" src-id="21003" dest-id="21318" weight="0.05771756172180176"/>
<connection id="21412" src-id="21004" dest-id="21318" weight="-0.6817777156829834"/>
<connection id="21413" src-id="21005" dest-id="21318" weight="-0.049422264099121094"/>
<connection id="21414" src-id="21006" dest-id="21318" weight="-0.4480193853378296"/>
<connection id="21415" src-id="21007" dest-id="21318" weight="-0.7964006662368774"/>
<connection id="21416" src-id="21008" dest-id="21318" weight="0.6959636211395264"/>
<connection id="21417" src-id="21009" dest-id="21318" weight="0.598207950592041"/>
<connection id="21418" src-id="21010" dest-id="21318" weight="-0.9597795009613037"/>
<connection id="21419" src-id="21011" dest-id="21318" weight="-0.06642556190490723"/>
<neuron id="21420" type="out" activation="sigmoid"/>
<connection id="21421" src-id="20911" dest-id="21420" weight="-0.4146076440811157"/>
<connection id="21422" src-id="20912" dest-id="21420" weight="-0.7852461338043213"/>
<connection id="21423" src-id="20913" dest-id="21420" weight="0.3942270278930664"/>
<connection id="21424" src-id="20914" dest-id="21420" weight="-0.960136890411377"/>
<connection id="21425" src-id="20915" dest-id="21420" weight="0.16282331943511963"/>
<connection id="21426" src-id="20916" dest-id="21420" weight="-0.4024714231491089"/>
<connection id="21427" src-id="20917" dest-id="21420" weight="0.4960583448410034"/>
<connection id="21428" src-id="20918" dest-id="21420" weight="0.4762321710586548"/>
<connection id="21429" src-id="20919" dest-id="21420" weight="-0.2341669797897339"/>
<connection id="21430" src-id="20920" dest-id="21420" weight="0.3405238389968872"/>
<connection id="21431" src-id="20921" dest-id="21420" weight="0.6043959856033325"/>
<connection id="21432" src-id="20922" dest-id="21420" weight="-0.3904329538345337"/>
<connection id="21433" src-id="20923" dest-id="21420" weight="-0.015540719032287598"/>
<connection id="21434" src-id="20924" dest-id="21420" weight="-0.7602354288101196"/>
<connection id="21435" src-id="20925" dest-id="21420" weight="0.5725280046463013"/>
<connection id="21436" src-id="20926" dest-id="21420" weight="-0.2000197172164917"/>
<connection id="21437" src-id="20927" dest-id="21420" weight="-0.776724100112915"/>
<connection id="21438" src-id="20928" dest-id="21420" weight="-0.3168148994445801"/>
<connection id="21439" src-id="20929" dest-id="21420" weight="0.6307693719863892"/>
<connection id="21440" src-id="20930" dest-id="21420" weight="-0.3342233896255493"/>
<connection id="21441" src-id="20931" dest-id="21420" weight="-0.32331180572509766"/>
<connection id="21442" src-id="20932" dest-id="21420" weight="-0.3773465156555176"/>
<connection id="21443" src-id="20933" dest-id="21420" weight="-0.9067089557647705"/>
<connection id="21444" src-id="20934" dest-id="21420" weight="0.7122056484222412"/>
<connection id="21445" src-id="20935" dest-id="21420" weight="-0.9609806537628174"/>
<connection id="21446" src-id="20936" dest-id="21420" weight="0.4786182641983032"/>
<connection id="21447" src-id="20937" dest-id="21420" weight="-0.03189074993133545"/>
<connection id="21448" src-id="20938" dest-id="21420" weight="-0.6631040573120117"/>
<connection id="21449" src-id="20939" dest-id="21420" weight="-0.6748994588851929"/>
<connection id="21450" src-id="20940" dest-id="21420" weight="-0.6647852659225464"/>
<connection id="21451" src-id="20941" dest-id="21420" weight="0.7475788593292236"/>
<connection id="21452" src-id="20942" dest-id="21420" weight="0.8455653190612793"/>
<connection id="21453" src-id="20943" dest-id="21420" weight="0.9237293004989624"/>
<connection id="21454" src-id="20944" dest-id="21420" weight="0.9615603685379028"/>
<connection id="21455" src-id="20945" dest-id="21420" weight="-0.519158124923706"/>
<connection id="21456" src-id="20946" dest-id="21420" weight="0.20069444179534912"/>
<connection id="21457" src-id="20947" dest-id="21420" weight="0.2443448305130005"/>
<connection id="21458" src-id="20948" dest-id="21420" weight="0.6156631708145142"/>
<connection id="21459" src-id="20949" dest-id="21420" weight="0.45624613761901855"/>
<connection id="21460" src-id="20950" dest-id="21420" weight="-0.6287897825241089"/>
<connection id="21461" src-id="20951" dest-id="21420" weight="-0.8733372688293457"/>
<connection id="21462" src-id="20952" dest-id="21420" weight="0.9793722629547119"/>
<connection id="21463" src-id="20953" dest-id="21420" weight="-0.14100515842437744"/>
<connection id="21464" src-id="20954" dest-id="21420" weight="-0.15299296379089355"/>
<connection id="21465" src-id="20955" dest-id="21420" weight="-0.574852705001831"/>
<connection id="21466" src-id="20956" dest-id="21420" weight="0.8208850622177124"/>
<connection id="21467" src-id="20957" dest-id="21420" weight="-0.9433555603027344"/>
<connection id="21468" src-id="20958" dest-id="21420" weight="0.028713345527648926"/>
<connection id="21469" src-id="20959" dest-id="21420" weight="-0.0023511648178100586"/>
<connection id="21470" src-id="20960" dest-id="21420" weight="0.6265045404434204"/>
<connection id="21471" src-id="20961" dest-id="21420" weight="0.673256516456604"/>
<connection id="21472" src-id="20962" dest-id="21420" weight="-0.3928549289703369"/>
<connection id="21473" src-id="20963" dest-id="21420" weight="0.6441315412521362"/>
<connection id="21474" src-id="20964" dest-id="21420" weight="-0.817118763923645"/>
<connection id="21475" src-id="20965" dest-id="21420" weight="-0.6560269594192505"/>
<connection id="21476" src-id="20966" dest-id="21420" weight="-0.07874894142150879"/>
<connection id="21477" src-id="20967" dest-id="21420" weight="-0.4377593994140625"/>
<connection id="21478" src-id="20968" dest-id="21420" weight="-0.7216111421585083"/>
<connection id="21479" src-id="20969" dest-id="21420" weight="0.5287319421768188"/>
<connection id="21480" src-id="20970" dest-id="21420" weight="0.7472002506256104"/>
<connection id="21481" src-id="20971" dest-id="21420" weight="-0.4021768569946289"/>
<connection id="21482" src-id="20972" dest-id="21420" weight="-0.16265571117401123"/>
<connection id="21483" src-id="20973" dest-id="21420" weight="0.5712189674377441"/>
<connection id="21484" src-id="20974" dest-id="21420" weight="-0.450023889541626"/>
<connection id="21485" src-id="20975" dest-id="21420" weight="-0.7619725465774536"/>
<connection id="21486" src-id="20976" dest-id="21420" weight="-0.9305095672607422"/>
<connection id="21487" src-id="20977" dest-id="21420" weight="-0.5873293876647949"/>
<connection id="21488" src-id="20978" dest-id="21420" weight="0.3540600538253784"/>
<connection id="21489" src-id="20979" dest-id="21420" weight="-0.02894008159637451"/>
<connection id="21490" src-id="20980" dest-id="21420" weight="-0.06819403171539307"/>
<connection id="21491" src-id="20981" dest-id="21420" weight="-0.8632471561431885"/>
<connection id="21492" src-id="20982" dest-id="21420" weight="-0.10059010982513428"/>
<connection id="21493" src-id="20983" dest-id="21420" weight="-0.3498227596282959"/>
<connection id="21494" src-id="20984" dest-id="21420" weight="-0.6612224578857422"/>
<connection id="21495" src-id="20985" dest-id="21420" weight="-0.5103561878204346"/>
<connection id="21496" src-id="20986" dest-id="21420" weight="-0.6129008531570435"/>
<connection id="21497" src-id="20987" dest-id="21420" weight="-0.03864777088165283"/>
<connection id="21498" src-id="20988" dest-id="21420" weight="-0.7444490194320679"/>
<connection id="21499" src-id="20989" dest-id="21420" weight="0.3780956268310547"/>
<connection id="21500" src-id="20990" dest-id="21420" weight="-0.9639265537261963"/>
<connection id="21501" src-id="20991" dest-id="21420" weight="0.3968554735183716"/>
<connection id="21502" src-id="20992" dest-id="21420" weight="-0.14312124252319336"/>
<connection id="21503" src-id="20993" dest-id="21420" weight="0.3183560371398926"/>
<connection id="21504" src-id="20994" dest-id="21420" weight="-0.07485496997833252"/>
<connection id="21505" src-id="20995" dest-id="21420" weight="0.4545654058456421"/>
<connection id="21506" src-id="20996" dest-id="21420" weight="-0.7192329168319702"/>
<connection id="21507" src-id="20997" dest-id="21420" weight="-0.8576700687408447"/>
<connection id="21508" src-id="20998" dest-id="21420" weight="-0.35453248023986816"/>
<connection id="21509" src-id="20999" dest-id="21420" weight="-0.42975378036499023"/>
<connection id="21510" src-id="21000" dest-id="21420" weight="0.7527108192443848"/>
<connection id="21511" src-id="21001" dest-id="21420" weight="0.7474731206893921"/>
<connection id="21512" src-id="21002" dest-id="21420" weight="0.5074644088745117"/>
<connection id="21513" src-id="21003" dest-id="21420" weight="0.7836278676986694"/>
<connection id="21514" src-id="21004" dest-id="21420" weight="0.7641582489013672"/>
<connection id="21515" src-id="21005" dest-id="21420" weight="-0.8819202184677124"/>
<connection id="21516" src-id="21006" dest-id="21420" weight="0.2079017162322998"/>
<connection id="21517" src-id="21007" dest-id="21420" weight="0.856478214263916"/>
<connection id="21518" src-id="21008" dest-id="21420" weight="-0.026617765426635742"/>
<connection id="21519" src-id="21009" dest-id="21420" weight="0.5935579538345337"/>
<connection id="21520" src-id="21010" dest-id="21420" weight="-0.3508493900299072"/>
<connection id="21521" src-id="21011" dest-id="21420" weight="-0.19920563697814941"/>
<neuron id="21522" type="out" activation="sigmoid"/>
<connection id="21523" src-id="20911" dest-id="21522" weight="0.13052010536193848"/>
<connection id="21524" src-id="20912" dest-id="21522" weight="0.7909351587295532"/>
<connection id="21525" src-id="20913" dest-id="21522" weight="0.10156428813934326"/>
<connection id="21526" src-id="20914" dest-id="21522" weight="0.11783719062805176"/>
<connection id="21527" src-id="20915" dest-id="21522" weight="0.8396856784820557"/>
<connection id="21528" src-id="20916" dest-id="21522" weight="0.612403392791748"/>
<connection id="21529" src-id="20917" dest-id="21522" weight="0.10543763637542725"/>
<connection id="21530" src-id="20918" dest-id="21522" weight="0.8553210496902466"/>
<connection id="21531" src-id="20919" dest-id="21522" weight="-0.2554609775543213"/>
<connection id="21532" src-id="20920" dest-id="21522" weight="-0.676347017288208"/>
<connection id="21533" src-id="20921" dest-id="21522" weight="0.8216139078140259"/>
<connection id="21534" src-id="20922" dest-id="21522" weight="-0.4967752695083618"/>
<connection id="21535" src-id="20923" dest-id="21522" weight="0.8005144596099854"/>
<connection id="21536" src-id="20924" dest-id="21522" weight="-0.7542423009872437"/>
<connection id="21537" src-id="20925" dest-id="21522" weight="0.266105055809021"/>
<connection id="21538" src-id="20926" dest-id="21522" weight="-0.8077598810195923"/>
<connection id="21539" src-id="20927" dest-id="21522" weight="-0.12565791606903076"/>
<connection id="21540" src-id="20928" dest-id="21522" weight="0.6644177436828613"/>
<connection id="21541" src-id="20929" dest-id="21522" weight="-0.2830345630645752"/>
<connection id="21542" src-id="20930" dest-id="21522" weight="-0.6621004343032837"/>
<connection id="21543" src-id="20931" dest-id="21522" weight="-0.15694952011108398"/>
<connection id="21544" src-id="20932" dest-id="21522" weight="-0.8413593769073486"/>
<connection id="21545" src-id="20933" dest-id="21522" weight="0.18027842044830322"/>
<connection id="21546" src-id="20934" dest-id="21522" weight="-0.7257537841796875"/>
<connection id="21547" src-id="20935" dest-id="21522" weight="0.6600927114486694"/>
<connection id="21548" src-id="20936" dest-id="21522" weight="0.7508989572525024"/>
<connection id="21549" src-id="20937" dest-id="21522" weight="-0.8281660079956055"/>
<connection id="21550" src-id="20938" dest-id="21522" weight="0.31111955642700195"/>
<connection id="21551" src-id="20939" dest-id="21522" weight="-0.8184138536453247"/>
<connection id="21552" src-id="20940" dest-id="21522" weight="-0.32184934616088867"/>
<connection id="21553" src-id="20941" dest-id="21522" weight="0.14357149600982666"/>
<connection id="21554" src-id="20942" dest-id="21522" weight="-0.4224604368209839"/>
<connection id="21555" src-id="20943" dest-id="21522" weight="0.7231903076171875"/>
<connection id="21556" src-id="20944" dest-id="21522" weight="0.8047946691513062"/>
<connection id="21557" src-id="20945" dest-id="21522" weight="0.9969894886016846"/>
<connection id="21558" src-id="20946" dest-id="21522" weight="0.8103752136230469"/>
<connection id="21559" src-id="20947" dest-id="21522" weight="-0.17363810539245605"/>
<connection id="21560" src-id="20948" dest-id="21522" weight="0.9028667211532593"/>
<connection id="21561" src-id="20949" dest-id="21522" weight="-0.47634291648864746"/>
<connection id="21562" src-id="20950" dest-id="21522" weight="-0.47620725631713867"/>
<connection id="21563" src-id="20951" dest-id="21522" weight="-0.8136025667190552"/>
<connection id="21564" src-id="20952" dest-id="21522" weight="-0.5989946126937866"/>
<connection id="21565" src-id="20953" dest-id="21522" weight="0.9460664987564087"/>
<connection id="21566" src-id="20954" dest-id="21522" weight="0.6434895992279053"/>
<connection id="21567" src-id="20955" dest-id="21522" weight="0.4248124361038208"/>
<connection id="21568" src-id="20956" dest-id="21522" weight="-0.5273467302322388"/>
<connection id="21569" src-id="20957" dest-id="21522" weight="0.5569919347763062"/>
<connection id="21570" src-id="20958" dest-id="21522" weight="-0.6157565116882324"/>
<connection id="21571" src-id="20959" dest-id="21522" weight="-0.17751216888427734"/>
<connection id="21572" src-id="20960" dest-id="21522" weight="-0.7524675130844116"/>
<connection id="21573" src-id="20961" dest-id="21522" weight="-0.2648348808288574"/>
<connection id="21574" src-id="20962" dest-id="21522" weight="0.8449329137802124"/>
<connection id="21575" src-id="20963" dest-id="21522" weight="0.37113308906555176"/>
<connection id="21576" src-id="20964" dest-id="21522" weight="0.7718771696090698"/>
<connection id="21577" src-id="20965" dest-id="21522" weight="0.21856582164764404"/>
<connection id="21578" src-id="20966" dest-id="21522" weight="-0.7717630863189697"/>
<connection id="21579" src-id="20967" dest-id="21522" weight="-0.1912318468093872"/>
<connection id="21580" src-id="20968" dest-id="21522" weight="-0.5733469724655151"/>
<connection id="21581" src-id="20969" dest-id="21522" weight="0.7193658351898193"/>
<connection id="21582" src-id="20970" dest-id="21522" weight="-0.2197202444076538"/>
<connection id="21583" src-id="20971" dest-id="21522" weight="-0.4039069414138794"/>
<connection id="21584" src-id="20972" dest-id="21522" weight="-0.31524932384490967"/>
<connection id="21585" src-id="20973" dest-id="21522" weight="0.9481804370880127"/>
<connection id="21586" src-id="20974" dest-id="21522" weight="-0.7126263380050659"/>
<connection id="21587" src-id="20975" dest-id="21522" weight="-0.8629032373428345"/>
<connection id="21588" src-id="20976" dest-id="21522" weight="0.22487163543701172"/>
<connection id="21589" src-id="20977" dest-id="21522" weight="0.4676783084869385"/>
<connection id="21590" src-id="20978" dest-id="21522" weight="0.3428175449371338"/>
<connection id="21591" src-id="20979" dest-id="21522" weight="0.677535891532898"/>
<connection id="21592" src-id="20980" dest-id="21522" weight="-0.07028329372406006"/>
<connection id="21593" src-id="20981" dest-id="21522" weight="0.010909795761108398"/>
<connection id="21594" src-id="20982" dest-id="21522" weight="-0.5322533845901489"/>
<connection id="21595" src-id="20983" dest-id="21522" weight="0.11378622055053711"/>
<connection id="21596" src-id="20984" dest-id="21522" weight="-0.3813948631286621"/>
<connection id="21597" src-id="20985" dest-id="21522" weight="0.8783265352249146"/>
<connection id="21598" src-id="20986" dest-id="21522" weight="-0.32111215591430664"/>
<connection id="21599" src-id="20987" dest-id="21522" weight="-0.04697287082672119"/>
<connection id="21600" src-id="20988" dest-id="21522" weight="0.47049689292907715"/>
<connection id="21601" src-id="20989" dest-id="21522" weight="-0.42397141456604004"/>
<connection id="21602" src-id="20990" dest-id="21522" weight="0.16657733917236328"/>
<connection id="21603" src-id="20991" dest-id="21522" weight="-0.4189572334289551"/>
<connection id="21604" src-id="20992" dest-id="21522" weight="-0.015490531921386719"/>
<connection id="21605" src-id="20993" dest-id="21522" weight="0.18917155265808105"/>
<connection id="21606" src-id="20994" dest-id="21522" weight="-0.41637468338012695"/>
<connection id="21607" src-id="20995" dest-id="21522" weight="0.16961956024169922"/>
<connection id="21608" src-id="20996" dest-id="21522" weight="0.5346235036849976"/>
<connection id="21609" src-id="20997" dest-id="21522" weight="-0.7821577787399292"/>
<connection id="21610" src-id="20998" dest-id="21522" weight="0.03589022159576416"/>
<connection id="21611" src-id="20999" dest-id="21522" weight="-0.49863994121551514"/>
<connection id="21612" src-id="21000" dest-id="21522" weight="0.6678097248077393"/>
<connection id="21613" src-id="21001" dest-id="21522" weight="-0.7365429401397705"/>
<connection id="21614" src-id="21002" dest-id="21522" weight="0.47633373737335205"/>
<connection id="21615" src-id="21003" dest-id="21522" weight="-0.1282731294631958"/>
<connection id="21616" src-id="21004" dest-id="21522" weight="0.3659822940826416"/>
<connection id="21617" src-id="21005" dest-id="21522" weight="-0.5265145301818848"/>
<connection id="21618" src-id="21006" dest-id="21522" weight="0.8846940994262695"/>
<connection id="21619" src-id="21007" dest-id="21522" weight="0.36855316162109375"/>
<connection id="21620" src-id="21008" dest-id="21522" weight="0.6689497232437134"/>
<connection id="21621" src-id="21009" dest-id="21522" weight="0.8689578771591187"/>
<connection id="21622" src-id="21010" dest-id="21522" weight="0.6948188543319702"/>
<connection id="21623" src-id="21011" dest-id="21522" weight="0.20660912990570068"/>
</chromosome>